Workbook

Sheet CTI-CMM Introduction
A1: Cyber Threat Intelligence Capability Maturity Model (CTI-CMM)
A2: The Cyber Threat Intelligence Capability Maturity Model (CTI-CMM) is designed to help improve cyber threat intelligence teams support to cybersecurity and risk management functions, leading to improved security outomes. Its goal is to provide a roadmap on how intelligence programs can mature existing support and process constructs to ultimately strengthen the organization's operational resilience. The CTI-CMM is industry sector, organization type, and size agnostic and was inspired by the U.S. Department of Energy's C2M2 cybersecurity framework. The CTI-CMM offers a stakeholder-first approach to CTI maturity. The CTI-CMM focuses on the implementation and management of CTI best practices associated with information technology (IT), operational technology (OT), and information assets and the environments in which they operate. The model can be used to: • Enable organizations to effectively and consistently evaluate and benchmark cyber threat intelligence capabilities • Improve organizational reach and support to cybersecurity and risk management stakeholders • Establish a roadmap to grow CTI program capabilities and improve existing maturity • Prioritize investment and actions to improve cyber threat intelligence capabilities • Share knowledge and best practices on CTI program operations
A3: The CTI-CMM Domains
A4: The CTI-CMM v1.1 is organized into 11 domains, comprised of two or more objectives. The objectives are target focus areas each containing a maturity rating using a scale of.four progressive CTI maturity indicator levels, CTI0 (Pre-Foundational) through CTI3 (Leading). 1. Asset, Change, and Configuration Management (ASSET) 2. Threat and Vulnerability Management (THREAT) 3. Risk Management (RISK) 4. Identity and Access Management (ACCESS) 5. Situational Awareness (SITUATION) 6. Event and Incident Response, Continuity of Operations (RESPONSE) 7. Third-Party Risk Management (THIRD-PARTIES) 8. Fraud and Abuse Management (FRAUD) 9. Workforce Management (WORKFORCE) 10. Cybersecurity Architecture (ARCHITECTURE) 11. Cybersecurity Program Management (PROGRAM)
D5: Version 1.3 / January 2026

Sheet Assessment Tool README
A1: Introduction to the Assessment Tool
A2: The CTI-CMM beta assessment tool is a stand-alone spreadsheet intended for users to download and use locally, so please download a copy of the read-only version on our website. Users self-evaluate their current maturity posture across each of the objective in a domain using the CTI0-CTI3 scale. In this tool, CTI0 represents no capability, CTI1 a partial implementation, CTI2 largely implemented, and CTI3 for fully implemented. The CTI-CMM self-assessment tool contains a master dashboard, which summarizes the results and dynamically populates as the user fills out scores across each domain. Each tab represents a domain in the CTI-CMM and lists the corresponding practice and maturity criteria for each of the levels. We recommend CTI programs perform an assessment using this tool at least bi-annually, often after end of year strategic planning and at the mid-point in the year to benchmark progress.
A3: Maturity Levels | B3: Domain Assessment
A4: The CTI-CMM uses a maturity level structure similar to the C2M2. Individual practices are listed within each level based on their maturity level characteristics. This enables CTI programs to assess their maturity based on their ability to perform specific practices in a manner that is repeatable and consistent. For example, in this model all practices at the CTI1 Foundational level should be basic, ad hoc, and unplanned with a focus on short-term results. The following is a summary of maturity level characteristics. | B4: The CTI-CMM Beta assessment is evaluate maturity level across 230 statements. Users can expect a fulsome CTI program reflection and evaluation to take approximately two hours. The only required inputs for each CTI-CMM domain is the evaluation score per objective. However, to support CTI program management and speed up future CTI-CMM assessments, we have created optional fields titled "Evidence", "POC", and "Notes". • The “Evidence” field is designed for users to identify supporting documenation and where it lives inside an organization. • The “POC” field represents the person, department, or owners of the evidence. • The “Notes” field is a free-form capture to annotate the reasoning behind why you made the assessment you did. Ex) Why did you rate your program at a 2 instead of a 3? What are you lacking? The more detail you put into your assessment now, the easier it will be to establish clear action plans for improvement.

Sheet Planning Sheet
A1: CTI-CMM Assessment Tool Planning Sheet
A3: What Is this | B3: To fully take advantage of the work done on each domain, this planning sheet is an opportunity to aggregate the highest priority items for prioritization based on the perceived LoE and Impact trade-offs.
A4: How-To | B4: 1. Complete your assessment of the domains, inclusive of Score, Goal Score, Level of Effort (to reach goal), Impact, and Target Date. 2. Once all domains are completed, locate to the "Priorities Summary Sheet" worksheet at the end of the domains. 3. Filter the D column to exclude "Below Threshold" values. 4. Copy the table of data there, starting at A4 and ending at O#, where # is the last row of the table. 5. Paste VALUES only into A11 in this sheet, and viola! Begin your journey solving CTI's most exciting opportunities.
A10: D-ID | B10: Domain | C10: Use-Cases | D10: Maturity level | E10: Practice | F10: SCORE | G10: MAX | H10: STATUS | I10: EVIDENCE | J10: POC | K10: Goal Score | L10: Est. Impact | M10: Est. LOE | N10: Priority | O10: Target Date

Sheet Dashboard
B1: Cyber Threat Intelligence Capability Maturity Model (CTI-CMM)
B3: Assessment Tool BETA (Version 1.3 January 2026)
B4: ="Total Questions : "&E18/3 -> Total Questions : 195
B5: DOMAIN SUBTOTALS | C5: NICKNAME | D5: SCORE | E5: MAX | F5: % Cmpl* | G5: Date Last Assessed* | H5: Domain in Use?
B6: 1. Asset, Change, and Configuration Management | C6: ASSET | D6: ='Domain 1 - ASSET'!D25 -> 0 | E6: ='Domain 1 - ASSET'!E25 -> 39 | F6: =D6/E6 -> 0 | G6: ='Domain 1 - ASSET'!G2 -> 46041 | H6: ='Domain 1 - ASSET'!G3 -> Yes
B7: 2. Threat and Vulnerability Management | C7: THREAT | D7: ='Domain 2 - THREAT'!D52 -> 0 | E7: ='Domain 2 - THREAT'!E52 -> 93 | F7: =D7/E7 -> 0 | G7: ='Domain 2 - THREAT'!G2 -> 46041 | H7: ='Domain 2 - THREAT'!G3 -> Yes
B8: 3. Risk Management | C8: RISK | D8: ='Domain 3 - RISK'!D28 -> 0 | E8: ='Domain 3 - RISK'!E28 -> 48 | F8: =D8/E8 -> 0 | G8: ='Domain 3 - RISK'!G2 -> 46041 | H8: ='Domain 3 - RISK'!G3 -> Yes
B9: 4. Identity and Access Management | C9: ACCESS | D9: ='Domain 4 - ACCESS'!D26 -> 0 | E9: ='Domain 4 - ACCESS'!E26 -> 42 | F9: =D9/E9 -> 0 | G9: ='Domain 4 - ACCESS'!G2 -> 1/19/2026 | H9: ='Domain 4 - ACCESS'!G3 -> Yes
B10: 5. Situational Awareness | C10: SITUATION | D10: ='Domain 5 - SITUATION'!D17 -> 0 | E10: ='Domain 5 - SITUATION'!E17 -> 24 | F10: =D10/E10 -> 0 | G10: ='Domain 5 - SITUATION'!G2 -> 1/19/2026 | H10: ='Domain 5 - SITUATION'!G3 -> Yes
B11: 6. Event and Incident Response, Continuity of Operations | C11: RESPONSE | D11: ='Domain 6 - RESPONSE'!D39 -> 0 | E11: ='Domain 6 - RESPONSE'!E39 -> 72 | F11: =D11/E11 -> 0 | G11: ='Domain 6 - RESPONSE'!G2 -> 1/19/2026 | H11: ='Domain 6 - RESPONSE'!G3 -> Yes
B12: 7. Third-Party Risk Management | C12: RISK | D12: ='Domain 7 - THIRD-PARTIES'!D30 -> 0 | E12: ='Domain 7 - THIRD-PARTIES'!E30 -> 45 | F12: =D12/E12 -> 0 | G12: ='Domain 7 - THIRD-PARTIES'!G2 -> 1/19/2026 | H12: ='Domain 7 - THIRD-PARTIES'!G3 -> Yes
B13: 8. Fraud and Abuse Management | C13: FRAUD | D13: ='Domain 8 - FRAUD'!D42 -> 0 | E13: ='Domain 8 - FRAUD'!E42 -> 81 | F13: =D13/E13 -> 0 | G13: ='Domain 8 - FRAUD'!G2 -> 1/19/2026 | H13: ='Domain 8 - FRAUD'!G3 -> Yes
B14: 9. Workforce Management | C14: WORKFORCE | D14: 0 | E14: ='Domain 9 - WORKFORCE'!E38 -> 69 | F14: =D14/E14 -> 0 | G14: ='Domain 9 - WORKFORCE'!G2 -> 1/19/2026 | H14: ='Domain 9 - WORKFORCE'!G3 -> Yes
B15: 10. Cybersecurity Architecture | C15: ARCHITECTURE | D15: ='Domain 10 - ARCHITECTURE'!D28 -> 0 | E15: ='Domain 10 - ARCHITECTURE'!E28 -> 39 | F15: =D15/E15 -> 0 | G15: ='Domain 10 - ARCHITECTURE'!G2 -> 1/19/2026 | H15: ='Domain 10 - ARCHITECTURE'!G3 -> Yes
B16: 11. Cybersecurity Program Management | C16: PROGRAM | D16: ='Domain 11 - PROGRAM'!D23 -> 0 | E16: ='Domain 11 - PROGRAM'!E23 -> 33 | F16: =D16/E16 -> 0 | G16: ='Domain 11 - PROGRAM'!G2 -> 1/19/2026 | H16: ='Domain 11 - PROGRAM'!G3 -> Yes
C18: Total | D18: =SUM(D6:D16) -> 0 | E18: =SUM(E6:E16) -> 585 | F18: =D18/E18 -> 0
B42: Notes:
B44: % Complete: 0-32.99% RED. 33-65.99% ORANGE. 66-100% GREEN.
B45: Date Last Assessed: The cell will be ORANGE if 90 days before review is due (One year). Will be RED if one year past day of last review.
B46: Domain in Use: Determined on Domain Page

Sheet Domain 1 - ASSET
B2: Cyber Threat Intelligence Capability Maturity Model (CTI-CMM) | F2: DATE LAST ASSESED | G2: 46041
F3: Domain is Relevant? | G3: Yes
B4: 1. Asset, Change, and Configuration Management (ASSET)
D5: SCORE | E5: MAX | F5: STATUS | G5: EVIDENCE | H5: POC | I5: NOTES
B6: 1. Asset Visibility
B7: CTI1 | C7: a. CTI has access to available asset inventory and uses that access at least in an ad hoc manner. In organizations where an asset inventory is limited — or does not exist — access and/or visibility may be limited to appropriate systems or based upon relationships with technology teams. | E7: =IF(D7="N/A","N/A",3) -> 3 | F7: =IF(D7=0, "Not Implemented",IF(D7=1,"Partially Implemented",IF(D7=2,"Largely Implemented",IF(D7=3,"Fully Implemented",IF(D7="N/A","N/A"))))) -> Not Implemented
B8: CTI2 | C8: b. CTI receives alerts concurrently with the asset management team and provides analysis to that team (and other stakeholders) on threats aligned with those newly discovered assets in a timely manner to communicate risk of exposure. | E8: =IF(D8="N/A","N/A",3) -> 3 | F8: =IF(D8=0, "Not Implemented",IF(D8=1,"Partially Implemented",IF(D8=2,"Largely Implemented",IF(D8=3,"Fully Implemented")))) -> Not Implemented
C9: c. Intelligence includes contextualized insights and threat assessments of potential future scenarios related to the organization’s IT and operational technology (OT) assets. (see THREAT) | E9: =IF(D9="N/A","N/A",3) -> 3 | F9: =IF(D9=0, "Not Implemented",IF(D9=1,"Partially Implemented",IF(D9=2,"Largely Implemented",IF(D9=3,"Fully Implemented")))) -> Not Implemented
C10: d. CTI proactively works with technology teams to identify and enhance the type of information included in asset inventory (such as hardware and software versions, type of information processed or stored by the system, business function supported, network environment details, and other information that can be used to assess criticality and risk). | E10: =IF(D10="N/A","N/A",3) -> 3 | F10: =IF(D10=0, "Not Implemented",IF(D10=1,"Partially Implemented",IF(D10=2,"Largely Implemented",IF(D10=3,"Fully Implemented")))) -> Not Implemented
B11: CTI3 | C11: e. Intelligence regularly includes prescriptive analysis and recommendations to support asset discovery and risk assessments. (see RISK and ARCHITECTURE) | E11: =IF(D11="N/A","N/A",3) -> 3 | F11: =IF(D11=0, "Not Implemented",IF(D11=1,"Partially Implemented",IF(D11=2,"Largely Implemented",IF(D11=3,"Fully Implemented")))) -> Not Implemented
C12: f. ASSET domain objectives focused on identifying and prioritizing mitigation efforts are regularly informed by CTI insights to ensure a comprehensive view of the organization’s ecosystem. | E12: =IF(D12="N/A","N/A",3) -> 3 | F12: =IF(D12=0, "Not Implemented",IF(D12=1,"Partially Implemented",IF(D12=2,"Largely Implemented",IF(D12=3,"Fully Implemented")))) -> Not Implemented
C13: Section Subtotal | D13: =SUM(D7:D12) -> 0 | E13: =SUM(E7:E12)-((COUNTIF(D7:D12,"N/A")*3)) -> 18 | F13: =D13/E13 -> 0
B15: 2. Safeguard Assets
B16: CTI1 | C16: a. CTI maintains an understanding of “crown jewels assets” informed based on potential to disrupt business operations and cyber threat landscape trends. This prioritization is based on asset targeting, criticality, vulnerability, and potential impact in case of attack or exposure. | E16: =IF(D16="N/A","N/A",3) -> 3 | F16: =IF(D16=0, "Not Implemented",IF(D16=1,"Partially Implemented",IF(D16=2,"Largely Implemented",IF(D16=3,"Fully Implemented",IF(D16="N/A","N/A"))))) -> Not Implemented
C17: b. CTI maintains regular visibility into changes in the cyber threat landscape, triaging intelligence sources to determine relevance and relative impact of newly discovered threat campaigns and vulnerabilities affecting organizational assets. (see THREAT) | E17: =IF(D17="N/A","N/A",3) -> 3 | F17: =IF(D17=0, "Not Implemented",IF(D17=1,"Partially Implemented",IF(D17=2,"Largely Implemented",IF(D17=3,"Fully Implemented",IF(D17="N/A","N/A"))))) -> Not Implemented
B18: CTI2 | C18: c. Intelligence supports proactive risk mitigation efforts by providing contextualized insights, predictive assessments, and alerting about threats and vulnerabilities that could affect priority assets. | E18: =IF(D18="N/A","N/A",3) -> 3 | F18: =IF(D18=0, "Not Implemented",IF(D18=1,"Partially Implemented",IF(D18=2,"Largely Implemented",IF(D18=3,"Fully Implemented",IF(D18="N/A","N/A"))))) -> Not Implemented
C19: d. Intelligence identifies vulnerabilities that directly affect priority assets, allowing the organization to prioritize patching efforts. (see THREAT) | E19: =IF(D19="N/A","N/A",3) -> 3 | F19: =IF(D19=0, "Not Implemented",IF(D19=1,"Partially Implemented",IF(D19=2,"Largely Implemented",IF(D19=3,"Fully Implemented",IF(D19="N/A","N/A"))))) -> Not Implemented
B20: CTI3 | C20: e. CTI includes prescriptive threat analysis and recommendations to protect current and pre-deployed assets and change configurations based on the threat environment. | E20: =IF(D20="N/A","N/A",3) -> 3 | F20: =IF(D20=0, "Not Implemented",IF(D20=1,"Partially Implemented",IF(D20=2,"Largely Implemented",IF(D20=3,"Fully Implemented",IF(D20="N/A","N/A"))))) -> Not Implemented
C21: f. ASSET domain risk reduction strategies are consistently informed by CTI insights. | E21: =IF(D21="N/A","N/A",3) -> 3 | F21: =IF(D21=0, "Not Implemented",IF(D21=1,"Partially Implemented",IF(D21=2,"Largely Implemented",IF(D21=3,"Fully Implemented",IF(D21="N/A","N/A"))))) -> Not Implemented
C22: g. CTI is consulted as part of the asset purchase cycle and provides insights to the organization about potential risks (e.g., specific hardware, software, or products that have been targeted in the past). | E22: =IF(D22="N/A","N/A",3) -> 3 | F22: =IF(D22=0, "Not Implemented",IF(D22=1,"Partially Implemented",IF(D22=2,"Largely Implemented",IF(D22=3,"Fully Implemented",IF(D22="N/A","N/A"))))) -> Not Implemented
C23: Section Subtotal | D23: =SUM(D16:D22) -> 0 | E23: =SUM(E16:E22)-((COUNTIF(D16:D22,"N/A")*3)) -> 21 | F23: =D23/E23 -> 0
C25: Domain Total | D25: =D13+D23 -> 0 | E25: =E13+E23 -> 39 | F25: =D25/E25 -> 0

Sheet Domain 2 - THREAT
B2: Cyber Threat Intelligence Capability Maturity Model (CTI-CMM) | F2: DATE LAST ASSESED | G2: 46041
F3: Domain is Relevant? | G3: Yes
B4: 2. Threat and Vulnerability Management (THREAT)
D5: SCORE | E5: MAX | F5: STATUS | G5: EVIDENCE | H5: POC | I5: NOTES
B6: 1. Enhance Attack Prevention and Preparedness
B7: CTI1 | C7: a. Indicators of compromise/behavior/attack (IoC/B/As) are collected from external threat reports and delivered to security operations teams at least in an ad hoc manner (e.g., over email) to support prevention and blocking. | E7: =IF(D7="N/A","N/A",3) -> 3 | F7: =IF(D7=0, "Not Implemented",IF(D7=1,"Partially Implemented",IF(D7=2,"Largely Implemented",IF(D7=3,"Fully Implemented",IF(D7="N/A","N/A"))))) -> Not Implemented
C8: b. Reduction of false positives is supported at least in an ad hoc manner when identified. | E8: =IF(D8="N/A","N/A",3) -> 3 | F8: =IF(D8=0, "Not Implemented",IF(D8=1,"Partially Implemented",IF(D8=2,"Largely Implemented",IF(D8=3,"Fully Implemented",IF(D8="N/A","N/A"))))) -> Not Implemented
C9: c. Ongoing collections of IoC/B/As is pruned at least in an ad hoc manner or based upon default platform (TIP, security information and event management (SIEM), etc.) expiration parameters. | E9: =IF(D9="N/A","N/A",3) -> 3 | F9: =IF(D9=0, "Not Implemented",IF(D9=1,"Partially Implemented",IF(D9=2,"Largely Implemented",IF(D9=3,"Fully Implemented",IF(D9="N/A","N/A"))))) -> Not Implemented
B10: CTI2 | C10: d. IoC/B/As are collected from external feeds (usually contextualized by specific types of threats, e.g., phishing hosts, botnets, command-and-control (C2) hosts) and delivered directly to security technologies (e.g., SIEM or firewall solutions) in a mostly automated fashion. | E10: =IF(D10="N/A","N/A",3) -> 3 | F10: =IF(D10=0, "Not Implemented",IF(D10=1,"Partially Implemented",IF(D10=2,"Largely Implemented",IF(D10=3,"Fully Implemented",IF(D10="N/A","N/A"))))) -> Not Implemented
C11: e. Collection of IoC/B/As is automatically ingested and pruned based upon a defined strategy that considers enterprise-specific characteristics, operational factors, and threat profile. Polling frequency occurs on a regular cadence. | E11: =IF(D11="N/A","N/A",3) -> 3 | F11: =IF(D11=0, "Not Implemented",IF(D11=1,"Partially Implemented",IF(D11=2,"Largely Implemented",IF(D11=3,"Fully Implemented",IF(D11="N/A","N/A"))))) -> Not Implemented
C12: f. Available threat context (e.g., type of threat, attack stage) also is provided to aid operator awareness, typically reliant on source materials as ground truth. | E12: =IF(D12="N/A","N/A",3) -> 3 | F12: =IF(D12=0, "Not Implemented",IF(D12=1,"Partially Implemented",IF(D12=2,"Largely Implemented",IF(D12=3,"Fully Implemented",IF(D12="N/A","N/A"))))) -> Not Implemented
B13: CTI3 | C13: g. IoC/B/As are collected at scale from external feeds covering most types of threats (e.g., phishing infrastructure, botnets, C2 hosts) and delivered directly to relevant security technologies automatically. | E13: 3 | F13: =IF(D13=0, "Not Implemented",IF(D13=1,"Partially Implemented",IF(D13=2,"Largely Implemented",IF(D13=3,"Fully Implemented")))) -> Not Implemented
C14: h. False positives are measured and fidelity is refined. Focus is on increasing the quality of IoC/B/As collected. | E14: 3 | F14: =IF(D14=0, "Not Implemented",IF(D14=1,"Partially Implemented",IF(D14=2,"Largely Implemented",IF(D14=3,"Fully Implemented")))) -> Not Implemented
C15: i. Threat context, based on internal ecosystem knowledge versus reliance solely on source material scoring (e.g., type of threat, attack stage, detection time stamps, impact for relevance) is provided for most indicators to aid operator awareness. | E15: 3 | F15: =IF(D15=0, "Not Implemented",IF(D15=1,"Partially Implemented",IF(D15=2,"Largely Implemented",IF(D15=3,"Fully Implemented")))) -> Not Implemented
C16: j. Ingested high-confidence indicators are integrated to aid in proactive defense activities. For example, adding to automation playbooks and triggering COAs where relevant (e.g., automating implementation of low-regret blocking or phishing response). | E16: 3 | F16: =IF(D16=0, "Not Implemented",IF(D16=1,"Partially Implemented",IF(D16=2,"Largely Implemented",IF(D16=3,"Fully Implemented")))) -> Not Implemented
C17: k. Original indicators are correlated with internal event data (e.g., SOC/incident response (IR) investigations), actioned elsewhere within the organization (e.g., via threat hunting), and may also be shared externally. | E17: 3 | F17: =IF(D17=0, "Not Implemented",IF(D17=1,"Partially Implemented",IF(D17=2,"Largely Implemented",IF(D17=3,"Fully Implemented")))) -> Not Implemented
C18: Section Subtotal | D18: =SUM(D7:D17) -> 0 | E18: =SUM(E7:E17)-((COUNTIF(D7:D17,"N/A")*3)) -> 33 | F18: =D18/E18 -> 0
B20: 2. Detection Engineering Improvements and Strategy Detection Engineering
B21: CTI1 | C21: a. Alerts about adversaries actively posing potential threats to the organization are delivered at least in an ad hoc manner to support new detection logic. | E21: =IF(D21="N/A","N/A",3) -> 3 | F21: =IF(D21=0, "Not Implemented",IF(D21=1,"Partially Implemented",IF(D21=2,"Largely Implemented",IF(D21=3,"Fully Implemented",IF(D21="N/A","N/A"))))) -> Not Implemented
B22: CTI2 | C22: b. Threat profiling is routinely developed to support gap analysis activities and prioritize detection controls based on relevant threats against the organization. | E22: =IF(D22="N/A","N/A",3) -> 3 | F22: =IF(D22=0, "Not Implemented",IF(D22=1,"Partially Implemented",IF(D22=2,"Largely Implemented",IF(D22=3,"Fully Implemented",IF(D22="N/A","N/A"))))) -> Not Implemented
C23: c. Continuous detection engineering improvements are supported by requests for information (RFIs) for CTI about specific gaps and vulnerabilities. | E23: =IF(D23="N/A","N/A",3) -> 3 | F23: =IF(D23=0, "Not Implemented",IF(D23=1,"Partially Implemented",IF(D23=2,"Largely Implemented",IF(D23=3,"Fully Implemented",IF(D23="N/A","N/A"))))) -> Not Implemented
B24: CTI3 | C24: d. Threat modeling is routinely developed to identify and contextualize priority threats relevant to the organization. | E24: =IF(D24="N/A","N/A",3) -> 3 | F24: =IF(D24=0, "Not Implemented",IF(D24=1,"Partially Implemented",IF(D24=2,"Largely Implemented",IF(D24=3,"Fully Implemented",IF(D24="N/A","N/A"))))) -> Not Implemented
C25: e. CTI products regularly drive detection opportunities based on threat modeling, event logs, and external reporting. | E25: =IF(D25="N/A","N/A",3) -> 3 | F25: =IF(D25=0, "Not Implemented",IF(D25=1,"Partially Implemented",IF(D25=2,"Largely Implemented",IF(D25=3,"Fully Implemented",IF(D25="N/A","N/A"))))) -> Not Implemented
C26: Section Subtotal | D26: =SUM(D21:D25) -> 0 | E26: =SUM(E21:E25)-((COUNTIF(D21:D25,"N/A")*3)) -> 15 | F26: =D26/E26 -> 0
B28: 3. Enhance Threat Hunting
B29: CTI1 | C29: a. Alerts about emerging atomic indicators are provided to generate awareness and reactive hunt operations at least in an ad hoc manner with minimal contextualization using open sources. | E29: =IF(D29="N/A","N/A",3) -> 3 | F29: =IF(D29=0, "Not Implemented",IF(D29=1,"Partially Implemented",IF(D29=2,"Largely Implemented",IF(D29=3,"Fully Implemented",IF(D29="N/A","N/A"))))) -> Not Implemented
C30: b. Threat hunts are prioritized manually based on emerging reporting of threat or vulnerability risks. | E30: =IF(D30="N/A","N/A",3) -> 3 | F30: =IF(D30=0, "Not Implemented",IF(D30=1,"Partially Implemented",IF(D30=2,"Largely Implemented",IF(D30=3,"Fully Implemented",IF(D30="N/A","N/A"))))) -> Not Implemented
B31: CTI2 | C31: c. Threat hunt operations are routinely informed by intelligence about threat actor TTPs and behaviors, contextualized using open and commercial sources. | E31: =IF(D31="N/A","N/A",3) -> 3 | F31: =IF(D31=0, "Not Implemented",IF(D31=1,"Partially Implemented",IF(D31=2,"Largely Implemented",IF(D31=3,"Fully Implemented",IF(D31="N/A","N/A"))))) -> Not Implemented
C32: d. Threat hunts are continuously prioritized based on priority intelligence requirements (PIRs) and vulnerabilities against critical assets. | E32: =IF(D32="N/A","N/A",3) -> 3 | F32: =IF(D32=0, "Not Implemented",IF(D32=1,"Partially Implemented",IF(D32=2,"Largely Implemented",IF(D32=3,"Fully Implemented",IF(D32="N/A","N/A"))))) -> Not Implemented
B33: CTI3 | C33: e. Threat hunting methodologies are used to generate RFIs and provide context for new, original threat hunting hypotheses/abstracts (see the TaHiTI Threat Hunting Methodology for further details). | E33: =IF(D33="N/A","N/A",3) -> 3 | F33: =IF(D33=0, "Not Implemented",IF(D33=1,"Partially Implemented",IF(D33=2,"Largely Implemented",IF(D33=3,"Fully Implemented",IF(D33="N/A","N/A"))))) -> Not Implemented
C34: Section Subtotal | D34: =SUM(D29:D33) -> 0 | E34: =SUM(E29:E33)-((COUNTIF(D29:D33,"N/A")*3)) -> 15 | F34: =D34/E34 -> 0
B36: 4. Inform Offensive Security Operations
B37: CTI1 | C37: a. Alerts about emerging tactics, techniques, and exploit campaigns are tested at least in an ad hoc manner with limited contextualization using open sources. | E37: =IF(D37="N/A","N/A",3) -> 3 | F37: =IF(D37=0, "Not Implemented",IF(D37=1,"Partially Implemented",IF(D37=2,"Largely Implemented",IF(D37=3,"Fully Implemented",IF(D37="N/A","N/A"))))) -> Not Implemented
B38: CTI2 | C38: b. Insights about novel techniques, procedures, and technical exploits, typically derived from open or commercial sources, are provided regularly to inform relevant offensive security operations. | E38: =IF(D38="N/A","N/A",3) -> 3 | F38: =IF(D38=0, "Not Implemented",IF(D38=1,"Partially Implemented",IF(D38=2,"Largely Implemented",IF(D38=3,"Fully Implemented",IF(D38="N/A","N/A"))))) -> Not Implemented
C39: c. Intelligence is typically focused on threats pertaining to the organization’s unique threat profile and provided with contextualization and/or code that enables replication of reported behaviors. | E39: =IF(D39="N/A","N/A",3) -> 3 | F39: =IF(D39=0, "Not Implemented",IF(D39=1,"Partially Implemented",IF(D39=2,"Largely Implemented",IF(D39=3,"Fully Implemented",IF(D39="N/A","N/A"))))) -> Not Implemented
B40: CTI3 | C40: d. Alerts about new and emerging attack procedures and technical exploits are delivered regularly and typically contain enough context to enable precise recreation of observed behaviors. | E40: 3 | F40: =IF(D40=0, "Not Implemented",IF(D40=1,"Partially Implemented",IF(D40=2,"Largely Implemented",IF(D40=3,"Fully Implemented",IF(D40="N/A","N/A"))))) -> Not Implemented
C41: e. Insights focus on threats pertaining to the organization’s unique threat profile but also novel procedures that may not yet be actively exploited in the wild (e.g., new exploits published on code repositories or acquired via closed sources such as underground forums). | E41: =IF(D41="N/A","N/A",3) -> 3 | F41: =IF(D41=0, "Not Implemented",IF(D41=1,"Partially Implemented",IF(D41=2,"Largely Implemented",IF(D41=3,"Fully Implemented",IF(D41="N/A","N/A"))))) -> Not Implemented
C42: f. Offensive security operations based on threat reporting inform ad hoc collection for missing context and discovered gaps are mitigated for threat prevention. | E42: =IF(D42="N/A","N/A",3) -> 3 | F42: =IF(D42=0, "Not Implemented",IF(D42=1,"Partially Implemented",IF(D42=2,"Largely Implemented",IF(D42=3,"Fully Implemented",IF(D42="N/A","N/A"))))) -> Not Implemented
C43: Section Subtotal | D43: =SUM(D37:D42) -> 0 | E43: =SUM(E37:E42)-((COUNTIF(D37:D42,"N/A")*3)) -> 18 | F43: =D43/E43 -> 0
B45: 5. Improve Patch Prioritization
B46: CTI1 | C46: a. Alerts are provided at least in an ad hoc manner for critical vulnerabilities that are experiencing viral popularity in mainstream open sources. | E46: =IF(D46="N/A","N/A",3) -> 3 | F46: =IF(D46=0, "Not Implemented",IF(D46=1,"Partially Implemented",IF(D46=2,"Largely Implemented",IF(D46=3,"Fully Implemented",IF(D46="N/A","N/A"))))) -> Not Implemented
B47: CTI2 | C47: b. Vulnerability management is consistently informed in a repeatable manner for critical and high vulnerabilities that are seeing viral popularity in mainstream open and cybercriminal underground sources. | E47: =IF(D47="N/A","N/A",3) -> 3 | F47: =IF(D47=0, "Not Implemented",IF(D47=1,"Partially Implemented",IF(D47=2,"Largely Implemented",IF(D47=3,"Fully Implemented",IF(D47="N/A","N/A"))))) -> Not Implemented
C48: c. Patch prioritization is influenced by availability of PoC code, observed active exploitation, and sought-after interest by adversaries observed in the dark or surface web. | E48: =IF(D48="N/A","N/A",3) -> 3 | F48: =IF(D48=0, "Not Implemented",IF(D48=1,"Partially Implemented",IF(D48=2,"Largely Implemented",IF(D48=3,"Fully Implemented",IF(D48="N/A","N/A"))))) -> Not Implemented
B49: CTI3 | C49: d. Patch management is consistently driven by routine CTI products that prescribe key patches or mitigations that need to be implemented based on the probability of exploitation against the enterprise. | E49: 3 | F49: =IF(D49=0, "Not Implemented",IF(D49=1,"Partially Implemented",IF(D49=2,"Largely Implemented",IF(D49=3,"Fully Implemented",IF(D49="N/A","N/A"))))) -> Not Implemented
C50: Section Subtotal | D50: =SUM(D46:D49) -> 0 | E50: =SUM(E46:E49)-((COUNTIF(D46:D49,"N/A")*3)) -> 12 | F50: =D50/E50 -> 0
C52: Domain Total | D52: =D18+D26+D34+D43+D50 -> 0 | E52: =E18+E26+E34+E43+E50 -> 93 | F52: =D52/E52 -> 0

Sheet Domain 3 - RISK
B2: Cyber Threat Intelligence Capability Maturity Model (CTI-CMM) | F2: DATE LAST ASSESED | G2: 46041
F3: Domain is Relevant? | G3: Yes
B4: 3. Risk Management (RISK)
D5: SCORE | E5: MAX | F5: STATUS | G5: EVIDENCE | H5: POC | I5: NOTES
B6: 1. Align CTI Practices to Risk Management Strategies
B7: CTI1 | C7: a. The main risks to the organization are understood and their relation to the risk management strategy, at least in a basic manner. | E7: =IF(D7="N/A","N/A",3) -> 3 | F7: =IF(D7=0, "Not Implemented",IF(D7=1,"Partially Implemented",IF(D7=2,"Largely Implemented",IF(D7=3,"Fully Implemented",IF(D7="N/A","N/A"))))) -> Not Implemented
C8: b. Collaboration with risk management stakeholders is conducted at least in an ad hoc manner. | E8: =IF(D8="N/A","N/A",3) -> 3 | F8: =IF(D8=0, "Not Implemented",IF(D8=1,"Partially Implemented",IF(D8=2,"Largely Implemented",IF(D8=3,"Fully Implemented",IF(D8="N/A","N/A"))))) -> Not Implemented
B9: CTI2 | C9: c. CTI practices have a focused alignment to the organization’s risk management strategy and framework, aligning inclusion of risk assessment (such as through the use of Binary Risk Analysis) within CTI products. | E9: =IF(D9="N/A","N/A",3) -> 3 | F9: =IF(D9=0, "Not Implemented",IF(D9=1,"Partially Implemented",IF(D9=2,"Largely Implemented",IF(D9=3,"Fully Implemented",IF(D9="N/A","N/A"))))) -> Not Implemented
C10: d. Meetings and engagements between CTI and risk management teams occur regularly. | E10: =IF(D10="N/A","N/A",3) -> 3 | F10: =IF(D10=0, "Not Implemented",IF(D10=1,"Partially Implemented",IF(D10=2,"Largely Implemented",IF(D10=3,"Fully Implemented",IF(D10="N/A","N/A"))))) -> Not Implemented
C11: e. CTI practices influence proactive adjustments to risk management strategies. | E11: =IF(D11="N/A","N/A",3) -> 3 | F11: =IF(D11=0, "Not Implemented",IF(D11=1,"Partially Implemented",IF(D11=2,"Largely Implemented",IF(D11=3,"Fully Implemented",IF(D11="N/A","N/A"))))) -> Not Implemented
B12: CTI3 | C12: f. CTI practices adhere to the risk framework adopted by the organization, such as NIST 800-30 and the NIST Cybersecurity Framework. | E12: =IF(D12="N/A","N/A",3) -> 3 | F12: =IF(D12=0, "Not Implemented",IF(D12=1,"Partially Implemented",IF(D12=2,"Largely Implemented",IF(D12=3,"Fully Implemented",IF(D12="N/A","N/A"))))) -> Not Implemented
C13: g. CTI insights are used to prioritize risk-based decisions and actions based upon the threat landscape (sometimes called a Cyber Threat Profile). (see THREAT) | E13: =IF(D13="N/A","N/A",3) -> 3 | F13: =IF(D13=0, "Not Implemented",IF(D13=1,"Partially Implemented",IF(D13=2,"Largely Implemented",IF(D13=3,"Fully Implemented",IF(D13="N/A","N/A"))))) -> Not Implemented
C14: h. CTI establishes ongoing alignment with risk management strategies with a focus on enhancing processes through automation. (see PROGRAM) | E14: 3 | F14: =IF(D14=0, "Not Implemented",IF(D14=1,"Partially Implemented",IF(D14=2,"Largely Implemented",IF(D14=3,"Fully Implemented",IF(D14="N/A","N/A"))))) -> Not Implemented
C15: Section Subtotal | D15: =SUM(D7:D14) -> 0 | E15: =SUM(E7:E14)-((COUNTIF(D7:D14,"N/A")*3)) -> 24 | F15: =D15/E15 -> 0
B17: 2. Improve Risk Decisions, Assessments, and Controls
B18: CTI1 | C18: a. Threats are identified, assessed, and prioritized at least in an ad hoc manner and often without alignment to the organization's risk management strategy. (see THREAT) | E18: =IF(D18="N/A","N/A",3) -> 3 | F18: =IF(D18=0, "Not Implemented",IF(D18=1,"Partially Implemented",IF(D18=2,"Largely Implemented",IF(D18=3,"Fully Implemented",IF(D18="N/A","N/A"))))) -> Not Implemented
C19: b. CTI has a basic understanding of organizational assets, controls, operating environment, and risk posture. | E19: =IF(D19="N/A","N/A",3) -> 3 | F19: =IF(D19=0, "Not Implemented",IF(D19=1,"Partially Implemented",IF(D19=2,"Largely Implemented",IF(D19=3,"Fully Implemented",IF(D19="N/A","N/A"))))) -> Not Implemented
C20: c. CTI insights are available to support risk assessments at least in an ad hoc manner. | E20: =IF(D20="N/A","N/A",3) -> 3 | F20: =IF(D20=0, "Not Implemented",IF(D20=1,"Partially Implemented",IF(D20=2,"Largely Implemented",IF(D20=3,"Fully Implemented",IF(D20="N/A","N/A"))))) -> Not Implemented
B21: CTI2 | C21: d. A process for integrating CTI into risk assessments is created and used to inform basic risk controls and mitigations efforts. | E21: =IF(D21="N/A","N/A",3) -> 3 | F21: =IF(D21=0, "Not Implemented",IF(D21=1,"Partially Implemented",IF(D21=2,"Largely Implemented",IF(D21=3,"Fully Implemented",IF(D21="N/A","N/A"))))) -> Not Implemented
C22: e. CTI insights are regularly leveraged within risk assessments. | E22: =IF(D22="N/A","N/A",3) -> 3 | F22: =IF(D22=0, "Not Implemented",IF(D22=1,"Partially Implemented",IF(D22=2,"Largely Implemented",IF(D22=3,"Fully Implemented",IF(D22="N/A","N/A"))))) -> Not Implemented
C23: f. Risk-based controls are intermittently assessed and adjusted using CTI insights. | E23: =IF(D23="N/A","N/A",3) -> 3 | F23: =IF(D23=0, "Not Implemented",IF(D23=1,"Partially Implemented",IF(D23=2,"Largely Implemented",IF(D23=3,"Fully Implemented",IF(D23="N/A","N/A"))))) -> Not Implemented
B24: CTI3 | C24: g. CTI practices provide proactive guidance for risk mitigation and management, including scenario planning and simulations. (see SITUATION) | E24: =IF(D24="N/A","N/A",3) -> 3 | F24: =IF(D24=0, "Not Implemented",IF(D24=1,"Partially Implemented",IF(D24=2,"Largely Implemented",IF(D24=3,"Fully Implemented",IF(D24="N/A","N/A"))))) -> Not Implemented
C25: h. Risk-based controls and decision-making processes are periodically evaluated and refined on an ongoing basis through the collaboration with CTI. | E25: =IF(D25="N/A","N/A",3) -> 3 | F25: =IF(D25=0, "Not Implemented",IF(D25=1,"Partially Implemented",IF(D25=2,"Largely Implemented",IF(D25=3,"Fully Implemented",IF(D25="N/A","N/A"))))) -> Not Implemented
C26: Section Subtotal | D26: =SUM(D18:D25) -> 0 | E26: =SUM(E18:E25)-((COUNTIF(D18:D25,"N/A")*3)) -> 24 | F26: =D26/E26 -> 0
C28: Domain Total | D28: =D15+D26 -> 0 | E28: =E15+E26 -> 48 | F28: =D28/E28 -> 0

Sheet Domain 4 - ACCESS
B2: Cyber Threat Intelligence Capability Maturity Model (CTI-CMM) | F2: DATE LAST ASSESED | G2: 1/19/2026
F3: Domain is Relevant? | G3: Yes
B4: 4. Identity and Access Management (ACCESS)
D5: SCORE | E5: MAX | F5: STATUS | G5: EVIDENCE | H5: POC | I5: NOTES
B6: 1. Accelerate Remediation of Identity-Related Threats
B7: CTI1 | C7: a. Alerts about leaked or compromised credentials and identities from open and commercial sources are collected and reviewed at least in an ad hoc manner. | E7: =IF(D7="N/A","N/A",3) -> 3 | F7: =IF(D7=0, "Not Implemented",IF(D7=1,"Partially Implemented",IF(D7=2,"Largely Implemented",IF(D7=3,"Fully Implemented",IF(D7="N/A","N/A"))))) -> Not Implemented
C8: b. Alerts about vulnerabilities impacting identity-related systems that threaten unauthorized access or identity compromise are collected and reviewed at least in an ad hoc manner for patch prioritization. (see THREAT) | E8: =IF(D8="N/A","N/A",3) -> 3 | F8: =IF(D8=0, "Not Implemented",IF(D8=1,"Partially Implemented",IF(D8=2,"Largely Implemented",IF(D8=3,"Fully Implemented",IF(D8="N/A","N/A"))))) -> Not Implemented
B9: CTI2 | C9: c. CTI assists with integration and automation of alert dissemination into repeatable workflows for ACCESS domain rapid assessment and response. | E9: =IF(D9="N/A","N/A",3) -> 3 | F9: =IF(D9=0, "Not Implemented",IF(D9=1,"Partially Implemented",IF(D9=2,"Largely Implemented",IF(D9=3,"Fully Implemented",IF(D9="N/A","N/A"))))) -> Not Implemented
C10: d. Intelligence and associated indicators related to emerging malware targeting identities and identity systems is delivered to enhance early warning detections and proactive mitigation measures. | E10: =IF(D10="N/A","N/A",3) -> 3 | F10: =IF(D10=0, "Not Implemented",IF(D10=1,"Partially Implemented",IF(D10=2,"Largely Implemented",IF(D10=3,"Fully Implemented",IF(D10="N/A","N/A"))))) -> Not Implemented
B11: CTI3 | C11: e. Continuous monitoring is extended to identity-related threats posed by third parties. (see THIRD-PARTIES) | E11: 3 | F11: =IF(D11=0, "Not Implemented",IF(D11=1,"Partially Implemented",IF(D11=2,"Largely Implemented",IF(D11=3,"Fully Implemented",IF(D11="N/A","N/A"))))) -> Not Implemented
C12: f. Intelligence on emerging threat actor TTPs is used for detecting anomalous activities related to user accounts, login attempts, or access patterns that may signal identity compromise. | E12: =IF(D12="N/A","N/A",3) -> 3 | F12: =IF(D12=0, "Not Implemented",IF(D12=1,"Partially Implemented",IF(D12=2,"Largely Implemented",IF(D12=3,"Fully Implemented",IF(D12="N/A","N/A"))))) -> Not Implemented
C13: g. Intelligence includes contextualized insights and threat assessments to continuously improve identity-related discovery practices and predict future scenarios to enhance detections. | E13: =IF(D13="N/A","N/A",3) -> 3 | F13: =IF(D13=0, "Not Implemented",IF(D13=1,"Partially Implemented",IF(D13=2,"Largely Implemented",IF(D13=3,"Fully Implemented",IF(D13="N/A","N/A"))))) -> Not Implemented
C14: Section Subtotal | D14: =SUM(D7:D13) -> 0 | E14: =SUM(E7:E13)-((COUNTIF(D7:D13,"N/A")*3)) -> 21 | F14: =D14/E14 -> 0
B16: 2. Fortify Identity and Access Protection
B17: CTI1 | C17: a. CTI maintains basic awareness and monitoring of identity-related threats to logical and physical access controls — including vulnerability exploitations and security control configurations — that lead to immediate COAs. | E17: =IF(D17="N/A","N/A",3) -> 3 | F17: =IF(D17=0, "Not Implemented",IF(D17=1,"Partially Implemented",IF(D17=2,"Largely Implemented",IF(D17=3,"Fully Implemented",IF(D17="N/A","N/A"))))) -> Not Implemented
C18: b. Collection is focused primarily on identity-related threats relevant specifically to the organization. | E18: =IF(D18="N/A","N/A",3) -> 3 | F18: =IF(D18=0, "Not Implemented",IF(D18=1,"Partially Implemented",IF(D18=2,"Largely Implemented",IF(D18=3,"Fully Implemented",IF(D18="N/A","N/A"))))) -> Not Implemented
B19: CTI2 | C19: c. CTI maintains a comprehensive understanding of identity-related threats to logical and physical access controls relevant to the organization’s high-risk assets. (see ASSET and RISK) | E19: =IF(D19="N/A","N/A",3) -> 3 | F19: =IF(D19=0, "Not Implemented",IF(D19=1,"Partially Implemented",IF(D19=2,"Largely Implemented",IF(D19=3,"Fully Implemented",IF(D19="N/A","N/A"))))) -> Not Implemented
C20: d. CTI insights regularly influence proactive adjustments to enhance access control requirements and thresholds based on the threat environment, including MFA strategies and password resets. | E20: =IF(D20="N/A","N/A",3) -> 3 | F20: =IF(D20=0, "Not Implemented",IF(D20=1,"Partially Implemented",IF(D20=2,"Largely Implemented",IF(D20=3,"Fully Implemented",IF(D20="N/A","N/A"))))) -> Not Implemented
C21: e. Collection is extended to focus on identity-related threats relevant to the organization’s industry and geographic representation. (see SITUATION) | E21: =IF(D21="N/A","N/A",3) -> 3 | F21: =IF(D21=0, "Not Implemented",IF(D21=1,"Partially Implemented",IF(D21=2,"Largely Implemented",IF(D21=3,"Fully Implemented",IF(D21="N/A","N/A"))))) -> Not Implemented
B22: CTI3 | C22: f. CTI insights regularly inform the creation of threat scenarios and simulations to test, validate, and adjust authentication and access controls and mitigations. (see THREAT) | E22: =IF(D22="N/A","N/A",3) -> 3 | F22: =IF(D22=0, "Not Implemented",IF(D22=1,"Partially Implemented",IF(D22=2,"Largely Implemented",IF(D22=3,"Fully Implemented",IF(D22="N/A","N/A"))))) -> Not Implemented
C23: g. CTI insights inform tabletop exercises that fortify response and mitigation efforts across the organization. (see PROGRAM) | E23: =IF(D23="N/A","N/A",3) -> 3 | F23: =IF(D23=0, "Not Implemented",IF(D23=1,"Partially Implemented",IF(D23=2,"Largely Implemented",IF(D23=3,"Fully Implemented",IF(D23="N/A","N/A"))))) -> Not Implemented
C24: Section Subtotal | D24: =SUM(D17:D23) -> 0 | E24: =SUM(E17:E23)-((COUNTIF(D17:D23,"N/A")*3)) -> 21 | F24: =D24/E24 -> 0
C26: Domain Total | D26: =D14+D24 -> 0 | E26: =E14+E24 -> 42 | F26: =D26/E26 -> 0

Sheet Domain 5 - SITUATION
B2: Cyber Threat Intelligence Capability Maturity Model (CTI-CMM) | F2: DATE LAST ASSESED | G2: 1/19/2026
F3: Domain is Relevant? | G3: Yes
B4: 5. Situational Awareness (SITUATION)
D5: SCORE | E5: MAX | F5: STATUS | G5: EVIDENCE | H5: POC | I5: NOTES
B6: 1. Maintain Comprehensive Understanding of the Cyber Threat Landscape (CTL)
B7: CTI1 | C7: a. Situational awareness alerts and updates are collected from open and trusted sources. | E7: =IF(D7="N/A","N/A",3) -> 3 | F7: =IF(D7=0, "Not Implemented",IF(D7=1,"Partially Implemented",IF(D7=2,"Largely Implemented",IF(D7=3,"Fully Implemented",IF(D7="N/A","N/A"))))) -> Not Implemented
C8: b. Insights are provided at least in an ad hoc manner for short-term trends and observations that lead to immediate courses of action (COAs). | E8: =IF(D8="N/A","N/A",3) -> 3 | F8: =IF(D8=0, "Not Implemented",IF(D8=1,"Partially Implemented",IF(D8=2,"Largely Implemented",IF(D8=3,"Fully Implemented",IF(D8="N/A","N/A"))))) -> Not Implemented
C9: c. Collection is focused primarily on all threats relevant specifically to the organization. (see THREAT) | E9: =IF(D9="N/A","N/A",3) -> 3 | F9: =IF(D9=0, "Not Implemented",IF(D9=1,"Partially Implemented",IF(D9=2,"Largely Implemented",IF(D9=3,"Fully Implemented",IF(D9="N/A","N/A"))))) -> Not Implemented
B10: CTI2 | C10: d. A systematic process, such as the one described in the ENISA Cybersecurity Threat Landscape Methodology, is implemented to routinely produce CTL reports. (see THREAT) | E10: =IF(D10="N/A","N/A",3) -> 3 | F10: =IF(D10=0, "Not Implemented",IF(D10=1,"Partially Implemented",IF(D10=2,"Largely Implemented",IF(D10=3,"Fully Implemented",IF(D10="N/A","N/A"))))) -> Not Implemented
C11: e. The CTL scope is mostly tactical and operational, delivering insights that provide short- to medium-term results. The audience and dissemination is to most enterprise stakeholder domains. The focus is primarily on priority threats and trends specific to the organization. CTL leverages priority intelligence requirements (PIRs) focused on tactical and operational needs. | E11: =IF(D11="N/A","N/A",3) -> 3 | F11: =IF(D11=0, "Not Implemented",IF(D11=1,"Partially Implemented",IF(D11=2,"Largely Implemented",IF(D11=3,"Fully Implemented",IF(D11="N/A","N/A"))))) -> Not Implemented
C12: f. Develops baseline for return on investment and cost-benefit analysis between sources and products. | E12: =IF(D12="N/A","N/A",3) -> 3 | F12: =IF(D12=0, "Not Implemented",IF(D12=1,"Partially Implemented",IF(D12=2,"Largely Implemented",IF(D12=3,"Fully Implemented",IF(D12="N/A","N/A"))))) -> Not Implemented
B13: CTI3 | C13: g. The CTL scope is extended to include deliverables that regularly provide actionable intelligence to inform long-term strategic decision-making and align with risk reduction strategies. The audience and dissemination is to all enterprise stakeholder domains based on PIRs. The focus is extended to include threats, events, and trends relevant to the organization’s industry and geographic representation. (see RISK, PROGRAM and THREAT) | E13: =IF(D13="N/A","N/A",3) -> 3 | F13: =IF(D13=0, "Not Implemented",IF(D13=1,"Partially Implemented",IF(D13=2,"Largely Implemented",IF(D13=3,"Fully Implemented",IF(D13="N/A","N/A"))))) -> Not Implemented
C14: i. CTI routinely validates sources, tracks impact, and engages in return on investment reviews for all sources leveraged. | E14: =IF(D14="N/A","N/A",3) -> 3 | F14: =IF(D14=0, "Not Implemented",IF(D14=1,"Partially Implemented",IF(D14=2,"Largely Implemented",IF(D14=3,"Fully Implemented",IF(D14="N/A","N/A"))))) -> Not Implemented
C15: Section Subtotal | D15: =SUM(D7:D14) -> 0 | E15: =SUM(E7:E14)-((COUNTIF(D7:D14,"N/A")*3)) -> 24 | F15: =D15/E15 -> 0
C17: Domain Total | D17: =D15 -> 0 | E17: =E15 -> 24 | F17: =D17/E17 -> 0

Sheet Domain 6 - RESPONSE
B2: Cyber Threat Intelligence Capability Maturity Model (CTI-CMM) | F2: DATE LAST ASSESED | G2: 1/19/2026
F3: Domain is Relevant? | G3: Yes
B4: 6. Event and Incident Response, Continuity of Operations (RESPONSE)
D5: SCORE | E5: MAX | F5: STATUS | G5: EVIDENCE | H5: POC | I5: NOTES
B6: 1. Strengthen Pre-Incident Preparedness
B7: CTI1 | C7: a. Event and incident data is collected for correlation with external open and trusted sources to enable detection and manual remediation of threats. | E7: =IF(D7="N/A","N/A",3) -> 3 | F7: =IF(D7=0, "Not Implemented",IF(D7=1,"Partially Implemented",IF(D7=2,"Largely Implemented",IF(D7=3,"Fully Implemented",IF(D7="N/A","N/A"))))) -> Not Implemented
C8: b. CTI insights and context are provided at least in an ad hoc manner to enrich event data, reduce false positives, and hasten response. | E8: =IF(D8="N/A","N/A",3) -> 3 | F8: =IF(D8=0, "Not Implemented",IF(D8=1,"Partially Implemented",IF(D8=2,"Largely Implemented",IF(D8=3,"Fully Implemented",IF(D8="N/A","N/A"))))) -> Not Implemented
B9: CTI2 | C9: c. The IR team swiftly enhances detected events through automated integration of CTI insights on threat actors, TTPs, enriched IOCs, and contextual information, significantly boosting response efficiency | E9: =IF(D9="N/A","N/A",3) -> 3 | F9: =IF(D9=0, "Not Implemented",IF(D9=1,"Partially Implemented",IF(D9=2,"Largely Implemented",IF(D9=3,"Fully Implemented",IF(D9="N/A","N/A"))))) -> Not Implemented
C10: d. CTI insights are used for immediate control gap detection analysis and rapid remediation, conducted in a mostly automated manner. | E10: =IF(D10="N/A","N/A",3) -> 3 | F10: =IF(D10=0, "Not Implemented",IF(D10=1,"Partially Implemented",IF(D10=2,"Largely Implemented",IF(D10=3,"Fully Implemented",IF(D10="N/A","N/A"))))) -> Not Implemented
B11: CTI3 | C11: e. CTI outputs (reports, alerts, enrichments) include assessments of the threat landscape and prescriptive recommendations to enable proactive detection controls and event response prioritization. (see SITUATION) | E11: =IF(D11="N/A","N/A",3) -> 3 | F11: =IF(D11=0, "Not Implemented",IF(D11=1,"Partially Implemented",IF(D11=2,"Largely Implemented",IF(D11=3,"Fully Implemented",IF(D11="N/A","N/A"))))) -> Not Implemented
C12: f. Tabletop and scenario exercises are informed by CTI insights of the latest malware, campaigns, vulnerabilities, and threats. (see RISK) | E12: =IF(D12="N/A","N/A",3) -> 3 | F12: =IF(D12=0, "Not Implemented",IF(D12=1,"Partially Implemented",IF(D12=2,"Largely Implemented",IF(D12=3,"Fully Implemented",IF(D12="N/A","N/A"))))) -> Not Implemented
C13: Section Subtotal | D13: =SUM(D7:D12) -> 0 | E13: =SUM(E7:E12)-((COUNTIF(D7:D12,"N/A")*3)) -> 18 | F13: =D13/E13 -> 0
B15: 2. Improve Incident Analysis and Response
B16: CTI1 | C16: a. Incident details are reviewed and mapped to a cyber kill chain or related industry framework (e.g., Lockheed Martin’s Cyber Kill Chain, MITRE ATT&CK, the Diamond Model of Intrusion Analysis, etc.). | E16: =IF(D16="N/A","N/A",3) -> 3 | F16: =IF(D16=0, "Not Implemented",IF(D16=1,"Partially Implemented",IF(D16=2,"Largely Implemented",IF(D16=3,"Fully Implemented",IF(D16="N/A","N/A"))))) -> Not Implemented
C17: b. Findings are documented as the incident progresses through the lifecycle phases. CTI insights are incorporated into the IR report. | E17: =IF(D17="N/A","N/A",3) -> 3 | F17: =IF(D17=0, "Not Implemented",IF(D17=1,"Partially Implemented",IF(D17=2,"Largely Implemented",IF(D17=3,"Fully Implemented",IF(D17="N/A","N/A"))))) -> Not Implemented
C18: c. Manual research and pivoting on TTPs and IoCs is being conducted to contextualize incidents and improve remediation, at least in an ad hoc manner. | E18: =IF(D18="N/A","N/A",3) -> 3 | F18: =IF(D18=0, "Not Implemented",IF(D18=1,"Partially Implemented",IF(D18=2,"Largely Implemented",IF(D18=3,"Fully Implemented",IF(D18="N/A","N/A"))))) -> Not Implemented
B19: CTI2 | C19: d. Findings are documented in a stand-alone CTI report and can be incorporated into or accompany the IR report. | E19: =IF(D19="N/A","N/A",3) -> 3 | F19: =IF(D19=0, "Not Implemented",IF(D19=1,"Partially Implemented",IF(D19=2,"Largely Implemented",IF(D19=3,"Fully Implemented",IF(D19="N/A","N/A"))))) -> Not Implemented
C20: e. Automation, which may include the use of machine learning or AI models, is used to enrich discovered indicators and map findings to cyber kill chains. | E20: =IF(D20="N/A","N/A",3) -> 3 | F20: =IF(D20=0, "Not Implemented",IF(D20=1,"Partially Implemented",IF(D20=2,"Largely Implemented",IF(D20=3,"Fully Implemented",IF(D20="N/A","N/A"))))) -> Not Implemented
B21: CTI3 | C21: f. Incident IoCs and related intelligence are ingested into a threat intelligence platform (TIP), using automation that maintains mapping verbosity to industry frameworks within the TIP’s ontology. This empowers orchestration to existing security controls for added enrichment and actions by appropriate controls teams. | E21: =IF(D21="N/A","N/A",3) -> 3 | F21: =IF(D21=0, "Not Implemented",IF(D21=1,"Partially Implemented",IF(D21=2,"Largely Implemented",IF(D21=3,"Fully Implemented",IF(D21="N/A","N/A"))))) -> Not Implemented
C22: g. Automation and process tools are used to trigger CTI analysis and escalation to the IR team. | E22: =IF(D22="N/A","N/A",3) -> 3 | F22: =IF(D22=0, "Not Implemented",IF(D22=1,"Partially Implemented",IF(D22=2,"Largely Implemented",IF(D22=3,"Fully Implemented",IF(D22="N/A","N/A"))))) -> Not Implemented
C23: h. Risk-based assessments and recommendations are routinely conveyed to the IR team. (see RISK) | E23: =IF(D23="N/A","N/A",3) -> 3 | F23: =IF(D23=0, "Not Implemented",IF(D23=1,"Partially Implemented",IF(D23=2,"Largely Implemented",IF(D23=3,"Fully Implemented",IF(D23="N/A","N/A"))))) -> Not Implemented
C24: Section Subtotal | D24: =SUM(D16:D23) -> 0 | E24: =SUM(E16:E23)-((COUNTIF(D16:D23,"N/A")*3)) -> 24 | F24: =D24/E24 -> 0
B26: 3. Enhance Post-Incident Recovery and Continuity of Operations
B27: CTI1 | C27: a. Incident findings, lessons learned, and improvement opportunities are captured within an internal knowledge base or ticket. Post-mortems are discussed internally and briefed to leadership at least in an ad hoc manner. | E27: =IF(D27="N/A","N/A",3) -> 3 | F27: =IF(D27=0, "Not Implemented",IF(D27=1,"Partially Implemented",IF(D27=2,"Largely Implemented",IF(D27=3,"Fully Implemented",IF(D27="N/A","N/A"))))) -> Not Implemented
C28: b. Manual ingestion and enrichment of intelligence, SOC internal indicators, and data occurs. | E28: =IF(D28="N/A","N/A",3) -> 3 | F28: =IF(D28=0, "Not Implemented",IF(D28=1,"Partially Implemented",IF(D28=2,"Largely Implemented",IF(D28=3,"Fully Implemented",IF(D28="N/A","N/A"))))) -> Not Implemented
C29: c. Partnership with the threat hunting team is initiated for ongoing collaboration. (see THREAT) | E29: =IF(D29="N/A","N/A",3) -> 3 | F29: =IF(D29=0, "Not Implemented",IF(D29=1,"Partially Implemented",IF(D29=2,"Largely Implemented",IF(D29=3,"Fully Implemented",IF(D29="N/A","N/A"))))) -> Not Implemented
B30: CTI2 | C30: d. Incident findings and lessons learned are regularly reviewed to spot trends and enhance security recommendations. Key insights are shared with leadership through briefings that emphasize the risks of inaction. | E30: =IF(D30="N/A","N/A",3) -> 3 | F30: =IF(D30=0, "Not Implemented",IF(D30=1,"Partially Implemented",IF(D30=2,"Largely Implemented",IF(D30=3,"Fully Implemented",IF(D30="N/A","N/A"))))) -> Not Implemented
C31: e. Incident response time is minimized through automation, implementing key prevention measures that utilize IoCs and TTPs from trusted sources. Automated CTI runbooks facilitate intelligence and event enrichment. | E31: =IF(D31="N/A","N/A",3) -> 3 | F31: =IF(D31=0, "Not Implemented",IF(D31=1,"Partially Implemented",IF(D31=2,"Largely Implemented",IF(D31=3,"Fully Implemented",IF(D31="N/A","N/A"))))) -> Not Implemented
C32: f. CTI maps enrich TTP findings from incident investigations by mapping them to the MITRE ATT&CK framework, allowing control teams to assess them against existing detection and prevention capabilities. Additionally, the enrichment of SOC internal indicators and data with intelligence is ongoing through TIP or automation. | E32: =IF(D32="N/A","N/A",3) -> 3 | F32: =IF(D32=0, "Not Implemented",IF(D32=1,"Partially Implemented",IF(D32=2,"Largely Implemented",IF(D32=3,"Fully Implemented",IF(D32="N/A","N/A"))))) -> Not Implemented
B33: CTI3 | C33: g. Artificial intelligence (AI) and machine learning (ML) are used for analysis of TTP mapping (MITRE TRAM). | E33: =IF(D33="N/A","N/A",3) -> 3 | F33: =IF(D33=0, "Not Implemented",IF(D33=1,"Partially Implemented",IF(D33=2,"Largely Implemented",IF(D33=3,"Fully Implemented",IF(D33="N/A","N/A"))))) -> Not Implemented
C34: h. Metrics are established and tuned based upon decisions made from incident post-mortems and related leadership actions. | E34: =IF(D34="N/A","N/A",3) -> 3 | F34: =IF(D34=0, "Not Implemented",IF(D34=1,"Partially Implemented",IF(D34=2,"Largely Implemented",IF(D34=3,"Fully Implemented",IF(D34="N/A","N/A"))))) -> Not Implemented
C35: i. Threat hunting activities are moderated by the CTI's assessment of prevalent TTPs for priority threat actors and runbooks are updated based on threat actor TTPs. (see THREAT) | E35: =IF(D35="N/A","N/A",3) -> 3 | F35: =IF(D35=0, "Not Implemented",IF(D35=1,"Partially Implemented",IF(D35=2,"Largely Implemented",IF(D35=3,"Fully Implemented",IF(D35="N/A","N/A"))))) -> Not Implemented
C36: j. Current and anticipated threats are disseminated to relevant security teams using daily or weekly reporting. | E36: =IF(D36="N/A","N/A",3) -> 3 | F36: =IF(D36=0, "Not Implemented",IF(D36=1,"Partially Implemented",IF(D36=2,"Largely Implemented",IF(D36=3,"Fully Implemented",IF(D36="N/A","N/A"))))) -> Not Implemented
C37: Section Subtotal | D37: =SUM(D27:D36) -> 0 | E37: =SUM(E27:E36)-((COUNTIF(D27:D36,"N/A")*3)) -> 30 | F37: =D37/E37 -> 0
C39: Domain Total | D39: =D13+D24+D37 -> 0 | E39: =E13+E24+E37 -> 72 | F39: =D39/E39 -> 0

Sheet Domain 7 - THIRD-PARTIES
B2: Cyber Threat Intelligence Capability Maturity Model (CTI-CMM) | F2: DATE LAST ASSESED | G2: 1/19/2026
F3: Domain is Relevant? | G3: Yes
B4: 7. Third-Party Risk Management (THIRD-PARTIES)
D5: SCORE | E5: MAX | F5: STATUS | G5: EVIDENCE | H5: POC | I5: NOTES
B7: 1. Assess Threats to Third Parties
B8: CTI1 | C8: a. CTI has access to a list of third-party vendors and suppliers. The list may be based on incidents or organization knowledge rather than a complete list. | E8: =IF(D8="N/A","N/A",3) -> 3 | F8: =IF(D8=0, "Not Implemented",IF(D8=1,"Partially Implemented",IF(D8=2,"Largely Implemented",IF(D8=3,"Fully Implemented",IF(D8="N/A","N/A"))))) -> Not Implemented
C9: b. CTI monitors data sources to assess the potential of third-party incidents at least in an ad hoc manner. | E9: =IF(D9="N/A","N/A",3) -> 3 | F9: =IF(D9=0, "Not Implemented",IF(D9=1,"Partially Implemented",IF(D9=2,"Largely Implemented",IF(D9=3,"Fully Implemented",IF(D9="N/A","N/A"))))) -> Not Implemented
B10: CTI2 | C10: c. Intelligence regarding threats to third parties is consistently contextualized to identify and mitigate risks. (see RISK and THREAT) | E10: =IF(D10="N/A","N/A",3) -> 3 | F10: =IF(D10=0, "Not Implemented",IF(D10=1,"Partially Implemented",IF(D10=2,"Largely Implemented",IF(D10=3,"Fully Implemented",IF(D10="N/A","N/A"))))) -> Not Implemented
C11: d. Third parties are prioritized based on established criteria, including factors such as business and information security risk. (see RISK) | E11: =IF(D11="N/A","N/A",3) -> 3 | F11: =IF(D11=0, "Not Implemented",IF(D11=1,"Partially Implemented",IF(D11=2,"Largely Implemented",IF(D11=3,"Fully Implemented",IF(D11="N/A","N/A"))))) -> Not Implemented
C12: e. Changes to the list of third-party vendors and suppliers are routinely updated and made available to CTI. | E12: =IF(D12="N/A","N/A",3) -> 3 | F12: =IF(D12=0, "Not Implemented",IF(D12=1,"Partially Implemented",IF(D12=2,"Largely Implemented",IF(D12=3,"Fully Implemented",IF(D12="N/A","N/A"))))) -> Not Implemented
C13: f. Intelligence from cybercriminal underground sources is monitored to evaluate third-party risks arising from compromises, stolen credentials, and intellectual property theft. (see RISK) | E13: =IF(D13="N/A","N/A",3) -> 3 | F13: =IF(D13=0, "Not Implemented",IF(D13=1,"Partially Implemented",IF(D13=2,"Largely Implemented",IF(D13=3,"Fully Implemented",IF(D13="N/A","N/A"))))) -> Not Implemented
B14: CTI3 | C14: g. CTI insights are used to update vendors and suppliers in a third-party risk management (TPRM) platform. (see RISK) | E14: =IF(D14="N/A","N/A",3) -> 3 | F14: =IF(D14=0, "Not Implemented",IF(D14=1,"Partially Implemented",IF(D14=2,"Largely Implemented",IF(D14=3,"Fully Implemented",IF(D14="N/A","N/A"))))) -> Not Implemented
C15: h. CTI supports the exposure analysis of suppliers and vendors involved in mergers or acquisitions. | E15: =IF(D15="N/A","N/A",3) -> 3 | F15: =IF(D15=0, "Not Implemented",IF(D15=1,"Partially Implemented",IF(D15=2,"Largely Implemented",IF(D15=3,"Fully Implemented",IF(D15="N/A","N/A"))))) -> Not Implemented
C16: i. Monitoring of changes in geopolitical risk is used to evaluate changes in threats to third parties. (see THREAT) | E16: =IF(D16="N/A","N/A",3) -> 3 | F16: =IF(D16=0, "Not Implemented",IF(D16=1,"Partially Implemented",IF(D16=2,"Largely Implemented",IF(D16=3,"Fully Implemented",IF(D16="N/A","N/A"))))) -> Not Implemented
C17: Section Subtotal | D17: =SUM(D8:D16) -> 0 | E17: =SUM(E8:E16)-((COUNTIF(D8:D16,"N/A")*3)) -> 27 | F17: =D17/E17 -> 0
B19: 2. Mitigate Third-Party Risk Exposure
B20: CTI1 | C20: a. CTI monitors and assesses potential third-party exposures at least in an ad hoc manner. | E20: =IF(D20="N/A","N/A",3) -> 3 | F20: =IF(D20=0, "Not Implemented",IF(D20=1,"Partially Implemented",IF(D20=2,"Largely Implemented",IF(D20=3,"Fully Implemented",IF(D20="N/A","N/A"))))) -> Not Implemented
C21: b. Intelligence concerning exploited vulnerabilities is routinely reviewed with respect to third-parties. | E21: =IF(D21="N/A","N/A",3) -> 3 | F21: =IF(D21=0, "Not Implemented",IF(D21=1,"Partially Implemented",IF(D21=2,"Largely Implemented",IF(D21=3,"Fully Implemented",IF(D21="N/A","N/A"))))) -> Not Implemented
B22: CTI2 | C22: c. CTI insights are used to assess risk of suppliers’ cybersecurity practices. (see RISK) | E22: =IF(D22="N/A","N/A",3) -> 3 | F22: =IF(D22=0, "Not Implemented",IF(D22=1,"Partially Implemented",IF(D22=2,"Largely Implemented",IF(D22=3,"Fully Implemented",IF(D22="N/A","N/A"))))) -> Not Implemented
C23: d. CTI continuously monitors and assesses potential exposures of business critical vendors and suppliers. | E23: =IF(D23="N/A","N/A",3) -> 3 | F23: =IF(D23=0, "Not Implemented",IF(D23=1,"Partially Implemented",IF(D23=2,"Largely Implemented",IF(D23=3,"Fully Implemented",IF(D23="N/A","N/A"))))) -> Not Implemented
C24: e. Intelligence includes predictive analysis about recommended COAs to reduce risk of exposure to the organization via third-party incidents. (see RISK) | E24: =IF(D24="N/A","N/A",3) -> 3 | F24: =IF(D24=0, "Not Implemented",IF(D24=1,"Partially Implemented",IF(D24=2,"Largely Implemented",IF(D24=3,"Fully Implemented",IF(D24="N/A","N/A"))))) -> Not Implemented
C25: f. CTI provides the SOC with TTPs and IoCs related to third-party breaches. | E25: =IF(D25="N/A","N/A",3) -> 3 | F25: =IF(D25=0, "Not Implemented",IF(D25=1,"Partially Implemented",IF(D25=2,"Largely Implemented",IF(D25=3,"Fully Implemented",IF(D25="N/A","N/A"))))) -> Not Implemented
B26: CTI3 | C26: g. CTI continuously monitors and assesses potential exposures of all vendors and suppliers. | E26: =IF(D26="N/A","N/A",3) -> 3 | F26: =IF(D26=0, "Not Implemented",IF(D26=1,"Partially Implemented",IF(D26=2,"Largely Implemented",IF(D26=3,"Fully Implemented",IF(D26="N/A","N/A"))))) -> Not Implemented
C27: h. Intelligence about third-party exposures is used prescriptively to identify future risk of the organization with existing third-parties and their associated technologies. (see RISK) | E27: =IF(D27="N/A","N/A",3) -> 3 | F27: =IF(D27=0, "Not Implemented",IF(D27=1,"Partially Implemented",IF(D27=2,"Largely Implemented",IF(D27=3,"Fully Implemented",IF(D27="N/A","N/A"))))) -> Not Implemented
C28: Section Subtotal | D28: =SUM(D20:D25) -> 0 | E28: =SUM(E20:E25)-((COUNTIF(D20:D25,"N/A")*3)) -> 18 | F28: =D28/E28 -> 0
C30: Domain Total | D30: =D17+D28 -> 0 | E30: =E17+E28 -> 45 | F30: =D30/E30 -> 0

Sheet Domain 8 - FRAUD
B2: Cyber Threat Intelligence Capability Maturity Model (CTI-CMM) | F2: DATE LAST ASSESED | G2: 1/19/2026
F3: Domain is Relevant? | G3: Yes
B4: 8. Fraud and Abuse Management (FRAUD)
D5: SCORE | E5: MAX | F5: STATUS | G5: EVIDENCE | H5: POC | I5: NOTES
B6: 1. Mitigate Financial Fraud
B7: CTI1 | C7: a. To combat exploitation and threat actor targeting, social media and open source sites are reviewed for posts of compromised customer credentials, gift cards, coupon scams, and credit cards at least in an ad hoc manner to support mitigation or prevention of fraudulent activity. | E7: 3 | F7: =IF(D7=0, "Not Implemented",IF(D7=1,"Partially Implemented",IF(D7=2,"Largely Implemented",IF(D7=3,"Fully Implemented",IF(D7="N/A","N/A"))))) -> Not Implemented
C8: b. CTI tracks the activity and any mentions of point-of-sale (PoS) credit card skimmers on forums and social media and supports relevant team(s) with remediation and response. | E8: 3 | F8: =IF(D8=0, "Not Implemented",IF(D8=1,"Partially Implemented",IF(D8=2,"Largely Implemented",IF(D8=3,"Fully Implemented",IF(D8="N/A","N/A"))))) -> Not Implemented
C9: c. Intelligence sharing groups and private chat channels are monitored for money mule notifications and actioned with the appropriate team(s). | E9: 3 | F9: =IF(D9=0, "Not Implemented",IF(D9=1,"Partially Implemented",IF(D9=2,"Largely Implemented",IF(D9=3,"Fully Implemented",IF(D9="N/A","N/A"))))) -> Not Implemented
C10: d. Information about adversary targeting toward customers, including brand impersonation and compromised credentials to facilitate fraud, is delivered in at least in an ad hoc manner. | E10: 3 | F10: =IF(D10=0, "Not Implemented",IF(D10=1,"Partially Implemented",IF(D10=2,"Largely Implemented",IF(D10=3,"Fully Implemented",IF(D10="N/A","N/A"))))) -> Not Implemented
C11: e. CTI is a member of trust groups (such as ISACs and peer sharing) focused on mitigating financial fraud. | E11: 3 | F11: =IF(D11=0, "Not Implemented",IF(D11=1,"Partially Implemented",IF(D11=2,"Largely Implemented",IF(D11=3,"Fully Implemented",IF(D11="N/A","N/A"))))) -> Not Implemented
B12: CTI2 | C12: f. Relevant information and data from trust groups is integrated into the organization's CTI practices. | E12: 3 | F12: =IF(D12=0, "Not Implemented",IF(D12=1,"Partially Implemented",IF(D12=2,"Largely Implemented",IF(D12=3,"Fully Implemented",IF(D12="N/A","N/A"))))) -> Not Implemented
C13: g. Automated monitoring is in place for mentions of common fraud indicators including business email compromise (BEC), short message service (SMS) phishing, invoice fraud, social engineering directed toward customers, and other relevant activity. | E13: 3 | F13: =IF(D13=0, "Not Implemented",IF(D13=1,"Partially Implemented",IF(D13=2,"Largely Implemented",IF(D13=3,"Fully Implemented",IF(D13="N/A","N/A"))))) -> Not Implemented
C14: h. CTI supports a cross-functional working group within the organization that is dedicated to identifying and sharing current and emerging threats on a recurring cadence. (see THREAT) | E14: 3 | F14: =IF(D14=0, "Not Implemented",IF(D14=1,"Partially Implemented",IF(D14=2,"Largely Implemented",IF(D14=3,"Fully Implemented",IF(D14="N/A","N/A"))))) -> Not Implemented
C15: i. Proactive tracking of fraud actor infrastructure and membership in private chat channels is done through automated collections and tooling. | E15: 3 | F15: =IF(D15=0, "Not Implemented",IF(D15=1,"Partially Implemented",IF(D15=2,"Largely Implemented",IF(D15=3,"Fully Implemented",IF(D15="N/A","N/A"))))) -> Not Implemented
B16: CTI3 | C16: j. Implementation of cyber deception methods, including honeypots and accounts, is used for adversary tracking and collecting intelligence on TTPs and IoCs. | E16: 3 | F16: =IF(D16=0, "Not Implemented",IF(D16=1,"Partially Implemented",IF(D16=2,"Largely Implemented",IF(D16=3,"Fully Implemented",IF(D16="N/A","N/A"))))) -> Not Implemented
C17: k. IoC/B/As collected related to observed financial fraud are automatically shared with trust groups (such as through a TIP or other tooling). | E17: 3 | F17: =IF(D17=0, "Not Implemented",IF(D17=1,"Partially Implemented",IF(D17=2,"Largely Implemented",IF(D17=3,"Fully Implemented",IF(D17="N/A","N/A"))))) -> Not Implemented
C18: l. Intelligence insights are used to create anti-fraud detections and regularly tuned based on the organization’s fraud observations. | E18: 3 | F18: =IF(D18=0, "Not Implemented",IF(D18=1,"Partially Implemented",IF(D18=2,"Largely Implemented",IF(D18=3,"Fully Implemented",IF(D18="N/A","N/A"))))) -> Not Implemented
C19: Section Subtotal | D19: =SUM(D7:D18) -> 0 | E19: =SUM(E7:E18)-((COUNTIF(D7:D18,"N/A")*3)) -> 36 | F19: =D19/E19 -> 0
B21: 2. Improve Brand Impersonation Protection
B22: CTI1 | C22: a. Manual intelligence collection and analysis is done at least in an ad hoc manner for adversary targeting including brand impersonation on corporate domains and social media accounts impersonating corporate brands and individuals. | E22: 3 | F22: =IF(D22=0, "Not Implemented",IF(D22=1,"Partially Implemented",IF(D22=2,"Largely Implemented",IF(D22=3,"Fully Implemented",IF(D22="N/A","N/A"))))) -> Not Implemented
C23: b. CTI insights inform decisions on a range of cybersecurity defenses, including MFA strategies (e.g., limiting SMS or phone-based authentication where possible) and other controls designed to disrupt brand impersonation attempts. | E23: 3 | F23: =IF(D23=0, "Not Implemented",IF(D23=1,"Partially Implemented",IF(D23=2,"Largely Implemented",IF(D23=3,"Fully Implemented",IF(D23="N/A","N/A"))))) -> Not Implemented
C24: c. CTI tracks threat actors associated with fraud and abuse targeting their brand(s). (see THREAT) | E24: 3 | F24: =IF(D24=0, "Not Implemented",IF(D24=1,"Partially Implemented",IF(D24=2,"Largely Implemented",IF(D24=3,"Fully Implemented",IF(D24="N/A","N/A"))))) -> Not Implemented
C25: d. CTI tracks phishing kits being used against the organization’s brand(s). | E25: 3 | F25: =IF(D25=0, "Not Implemented",IF(D25=1,"Partially Implemented",IF(D25=2,"Largely Implemented",IF(D25=3,"Fully Implemented",IF(D25="N/A","N/A"))))) -> Not Implemented
B26: CTI2 | C26: e. Automation is used to detect malvertising campaigns and SEO poisoning for disruption actions. | E26: 3 | F26: =IF(D26=0, "Not Implemented",IF(D26=1,"Partially Implemented",IF(D26=2,"Largely Implemented",IF(D26=3,"Fully Implemented",IF(D26="N/A","N/A"))))) -> Not Implemented
C27: f. Automated alerting for adversary targeting, including brand impersonation, is used. | E27: 3 | F27: =IF(D27=0, "Not Implemented",IF(D27=1,"Partially Implemented",IF(D27=2,"Largely Implemented",IF(D27=3,"Fully Implemented",IF(D27="N/A","N/A"))))) -> Not Implemented
C28: g. Information shared in trust groups is utilized to track and mitigate risk from specific threat actors and campaigns. (see RISK) | E28: 3 | F28: =IF(D28=0, "Not Implemented",IF(D28=1,"Partially Implemented",IF(D28=2,"Largely Implemented",IF(D28=3,"Fully Implemented",IF(D28="N/A","N/A"))))) -> Not Implemented
B29: CTI3 | C29: h. Automated identification and disruption of phishing kits targeting the organization’s brand(s) is used. | E29: 3 | F29: =IF(D29=0, "Not Implemented",IF(D29=1,"Partially Implemented",IF(D29=2,"Largely Implemented",IF(D29=3,"Fully Implemented",IF(D29="N/A","N/A"))))) -> Not Implemented
C30: i. CTI provides actionable intelligence for implementation of canary tokens on Amazon Web Services (AWS) keys, sensitive documents, hostnames, and URLs (web app exposed) to detect unwanted access or attempts to access. | E30: 3 | F30: =IF(D30=0, "Not Implemented",IF(D30=1,"Partially Implemented",IF(D30=2,"Largely Implemented",IF(D30=3,"Fully Implemented",IF(D30="N/A","N/A"))))) -> Not Implemented
C31: Section Subtotal | D31: =SUM(D22:D30) -> 0 | E31: =SUM(E22:E30)-((COUNTIF(D22:D30,"N/A")*3)) -> 27 | F31: =D31/E31 -> 0
B33: 3. Enhance Account Takeover Protection
B34: CTI1 | C34: a. CTI tracks forums, sites, and threat actors associated with fraud and abuse targeting their brand(s) to facilitate customer ATO attacks. | E34: 3 | F34: =IF(D34=0, "Not Implemented",IF(D34=1,"Partially Implemented",IF(D34=2,"Largely Implemented",IF(D34=3,"Fully Implemented",IF(D34="N/A","N/A"))))) -> Not Implemented
C35: b. Manual identification of leaked customer credentials and accounts for sale on forums, social media, or websites is sent to relevant teams for immediate action. | E35: 3 | F35: =IF(D35=0, "Not Implemented",IF(D35=1,"Partially Implemented",IF(D35=2,"Largely Implemented",IF(D35=3,"Fully Implemented",IF(D35="N/A","N/A"))))) -> Not Implemented
B36: CTI2 | C36: c. CTI provides intelligence to drive the creation of fraud-specific automation and detections for anomalous customer sign-ins and sessions indicating potential ATO activity. | E36: 3 | F36: =IF(D36=0, "Not Implemented",IF(D36=1,"Partially Implemented",IF(D36=2,"Largely Implemented",IF(D36=3,"Fully Implemented",IF(D36="N/A","N/A"))))) -> Not Implemented
C37: d. Feedback loops are created to include CTI when users (customers and employees) report suspicious behavior indicative of customer ATO activity. | E37: 3 | F37: =IF(D37=0, "Not Implemented",IF(D37=1,"Partially Implemented",IF(D37=2,"Largely Implemented",IF(D37=3,"Fully Implemented",IF(D37="N/A","N/A"))))) -> Not Implemented
B38: CTI3 | C38: e. CTI continuously delivers intelligence to drive the proactive deployment of cyber deception technologies (e.g., honeypots, canary tokens, honey accounts) and prescribe prevention methods that enable rapid containment of customer credential misuse. | E38: 3 | F38: =IF(D38=0, "Not Implemented",IF(D38=1,"Partially Implemented",IF(D38=2,"Largely Implemented",IF(D38=3,"Fully Implemented",IF(D38="N/A","N/A"))))) -> Not Implemented
C39: f. CTI provides intelligence on likely threat activity to support penetration tests and purple and red team engagements to test for social engineering (cyber and physical) and actively audit security controls. | E39: 3 | F39: =IF(D39=0, "Not Implemented",IF(D39=1,"Partially Implemented",IF(D39=2,"Largely Implemented",IF(D39=3,"Fully Implemented",IF(D39="N/A","N/A"))))) -> Not Implemented
C40: Section Subtotal | D40: =SUM(D34:D39) -> 0 | E40: =SUM(E34:E39)-((COUNTIF(D34:D39,"N/A")*3)) -> 18 | F40: =D40/E40 -> 0
C42: Domain Total | D42: =D19+D31+D40 -> 0 | E42: =E19+E31+E40 -> 81 | F42: =D42/E42 -> 0

Sheet Domain 9 - WORKFORCE
B2: Cyber Threat Intelligence Capability Maturity Model (CTI-CMM) | F2: DATE LAST ASSESED | G2: 1/19/2026
F3: Domain is Relevant? | G3: Yes
B4: 6.8 Workforce Management (WORKFORCE)
D5: SCORE | E5: MAX | F5: STATUS | G5: EVIDENCE | H5: POC | I5: NOTES
B6: 1. Support and Safeguard Human Resources Practices
B7: CTI1 | C7: a. CTI insights are regularly used to inform cybersecurity awareness and skills assessment strategies. | E7: =IF(D7="N/A","N/A",3) -> 3 | F7: =IF(D7=0, "Not Implemented",IF(D7=1,"Partially Implemented",IF(D7=2,"Largely Implemented",IF(D7=3,"Fully Implemented",IF(D7="N/A","N/A"))))) -> Not Implemented
C8: b. Direct communications — and at least periodic engagement — with workforce management leadership consistently help identify cyber-related skills required for safe and effective operations of the workforce. | E8: =IF(D8="N/A","N/A",3) -> 3 | F8: =IF(D8=0, "Not Implemented",IF(D8=1,"Partially Implemented",IF(D8=2,"Largely Implemented",IF(D8=3,"Fully Implemented",IF(D8="N/A","N/A"))))) -> Not Implemented
B9: CTI2 | C9: c. On a periodic basis, CTI provides inputs to personnel vetting/screening procedures to inform hiring decisions and to minimize potential insider threat risks. | E9: =IF(D9="N/A","N/A",3) -> 3 | F9: =IF(D9=0, "Not Implemented",IF(D9=1,"Partially Implemented",IF(D9=2,"Largely Implemented",IF(D9=3,"Fully Implemented",IF(D9="N/A","N/A"))))) -> Not Implemented
C10: d. CTI insights are consistently applied to inform the development of organization-specific plans for data/technology access needs, separation, and transfer procedures. | E10: =IF(D10="N/A","N/A",3) -> 3 | F10: =IF(D10=0, "Not Implemented",IF(D10=1,"Partially Implemented",IF(D10=2,"Largely Implemented",IF(D10=3,"Fully Implemented",IF(D10="N/A","N/A"))))) -> Not Implemented
B11: CTI3 | C11: e. Personnel vetting procedures are tailored to individual positions based on risk analysis (see RISK) of the job role and the organization’s threat profile. (see THREAT) | E11: =IF(D11="N/A","N/A",3) -> 3 | F11: =IF(D11=0, "Not Implemented",IF(D11=1,"Partially Implemented",IF(D11=2,"Largely Implemented",IF(D11=3,"Fully Implemented",IF(D11="N/A","N/A"))))) -> Not Implemented
C12: f. Screening tools used to assess the cybersecurity awareness of candidates and inform follow-on/remedial training requirements are developed and updated with CTI insights. | E12: =IF(D12="N/A","N/A",3) -> 3 | F12: =IF(D12=0, "Not Implemented",IF(D12=1,"Partially Implemented",IF(D12=2,"Largely Implemented",IF(D12=3,"Fully Implemented",IF(D12="N/A","N/A"))))) -> Not Implemented
C13: Section Subtotal | D13: =SUM(D7:D12) -> 0 | E13: =SUM(E7:E12)-((COUNTIF(D7:D12,"N/A")*3)) -> 18 | F13: =D13/E13 -> 0
B15: 2. Support Development of Training and Education Assets
B16: CTI1 | C16: a. Working relationships with the teams handling development and delivery of workforce training/education have been developed and engagement occurs at least in an ad hoc manner. | E16: =IF(D16="N/A","N/A",3) -> 3 | F16: =IF(D16=0, "Not Implemented",IF(D16=1,"Partially Implemented",IF(D16=2,"Largely Implemented",IF(D16=3,"Fully Implemented",IF(D16="N/A","N/A"))))) -> Not Implemented
C17: b. Insights provided by the CTI program are generally relevant to the organization, but not necessarily aligned to specific organizational units or job roles. | E17: =IF(D17="N/A","N/A",3) -> 3 | F17: =IF(D17=0, "Not Implemented",IF(D17=1,"Partially Implemented",IF(D17=2,"Largely Implemented",IF(D17=3,"Fully Implemented",IF(D17="N/A","N/A"))))) -> Not Implemented
C18: c. Workforce training/education initiatives are supported by CTI insights at least in an ad hoc manner and primarily related to significant changes in threat or vulnerability activity. (see THREAT) | E18: =IF(D18="N/A","N/A",3) -> 3 | F18: =IF(D18=0, "Not Implemented",IF(D18=1,"Partially Implemented",IF(D18=2,"Largely Implemented",IF(D18=3,"Fully Implemented",IF(D18="N/A","N/A"))))) -> Not Implemented
B19: CTI2 | C19: d. Security policy guidance, such as data protection and secure communication practices, is regularly reviewed by the CTI program — as are IR findings and other security reporting — to determine alignment of training/education initiatives with observed threat activity. | E19: =IF(D19="N/A","N/A",3) -> 3 | F19: =IF(D19=0, "Not Implemented",IF(D19=1,"Partially Implemented",IF(D19=2,"Largely Implemented",IF(D19=3,"Fully Implemented",IF(D19="N/A","N/A"))))) -> Not Implemented
C20: e. Training/education teams are engaged on a routine basis to ensure alignment of materials and approaches with the organization’s threat profile. | E20: =IF(D20="N/A","N/A",3) -> 3 | F20: =IF(D20=0, "Not Implemented",IF(D20=1,"Partially Implemented",IF(D20=2,"Largely Implemented",IF(D20=3,"Fully Implemented",IF(D20="N/A","N/A"))))) -> Not Implemented
C21: f. CTI products and insights are routinely integrated into cybersecurity training and education efforts. | E21: =IF(D21="N/A","N/A",3) -> 3 | F21: =IF(D21=0, "Not Implemented",IF(D21=1,"Partially Implemented",IF(D21=2,"Largely Implemented",IF(D21=3,"Fully Implemented",IF(D21="N/A","N/A"))))) -> Not Implemented
C22: g. Cybersecurity training materials are regularly reviewed by CTI to ensure the knowledge, skill, and ability gaps addressed in the curriculum are aligned with the organization’s threat profile. | E22: =IF(D22="N/A","N/A",3) -> 3 | F22: =IF(D22=0, "Not Implemented",IF(D22=1,"Partially Implemented",IF(D22=2,"Largely Implemented",IF(D22=3,"Fully Implemented",IF(D22="N/A","N/A"))))) -> Not Implemented
B23: CTI3 | C23: h. CTI insights are used to assist with tailoring cybersecurity awareness activities to individual job roles as appropriate for the organization’s threat profile. (see THREAT) | E23: =IF(D23="N/A","N/A",3) -> 3 | F23: =IF(D23=0, "Not Implemented",IF(D23=1,"Partially Implemented",IF(D23=2,"Largely Implemented",IF(D23=3,"Fully Implemented",IF(D23="N/A","N/A"))))) -> Not Implemented
C24: i. The continuous improvement of training programs and education materials is facilitated by CTI insights into the current and anticipated threat landscape. (see PROGRAM) | E24: =IF(D24="N/A","N/A",3) -> 3 | F24: =IF(D24=0, "Not Implemented",IF(D24=1,"Partially Implemented",IF(D24=2,"Largely Implemented",IF(D24=3,"Fully Implemented",IF(D24="N/A","N/A"))))) -> Not Implemented
C25: j. CTI insights are regularly leveraged for simulation exercises including phishing and social-engineering attacks. (see THREAT) | E25: =IF(D25="N/A","N/A",3) -> 3 | F25: =IF(D25=0, "Not Implemented",IF(D25=1,"Partially Implemented",IF(D25=2,"Largely Implemented",IF(D25=3,"Fully Implemented",IF(D25="N/A","N/A"))))) -> Not Implemented
C26: k. Regular review and evaluation is conducted to measure the effectiveness of CTI inclusion in workforce development efforts and improvements are made as appropriate. | E26: =IF(D26="N/A","N/A",3) -> 3 | F26: =IF(D26=0, "Not Implemented",IF(D26=1,"Partially Implemented",IF(D26=2,"Largely Implemented",IF(D26=3,"Fully Implemented",IF(D26="N/A","N/A"))))) -> Not Implemented
C27: Section Subtotal | D27: =SUM(D16:D26) -> 0 | E27: =SUM(E16:E26)-((COUNTIF(D16:D26,"N/A")*3)) -> 33 | F27: =D27/E27 -> 0
B29: 3. Support Cybersecurity Management in Workforce Development Efforts
B30: CTI1 | C30: a. Workforce development efforts are understood by the CTI program and it provides management with inputs as requested. | E30: =IF(D30="N/A","N/A",3) -> 3 | F30: =IF(D30=0, "Not Implemented",IF(D30=1,"Partially Implemented",IF(D30=2,"Largely Implemented",IF(D30=3,"Fully Implemented",IF(D30="N/A","N/A"))))) -> Not Implemented
B31: CTI2 | C31: b. The effort to identify high-risk job roles and support management in developing workforce-centric mitigation strategies is led by the CTI program. | E31: =IF(D31="N/A","N/A",3) -> 3 | F31: =IF(D31=0, "Not Implemented",IF(D31=1,"Partially Implemented",IF(D31=2,"Largely Implemented",IF(D31=3,"Fully Implemented",IF(D31="N/A","N/A"))))) -> Not Implemented
C32: c. Procedures and activities associated with CTI support to workforce management efforts are documented, followed, and maintained to ensure effective and ongoing support. | E32: =IF(D32="N/A","N/A",3) -> 3 | F32: =IF(D32=0, "Not Implemented",IF(D32=1,"Partially Implemented",IF(D32=2,"Largely Implemented",IF(D32=3,"Fully Implemented",IF(D32="N/A","N/A"))))) -> Not Implemented
B33: CTI3 | C33: d. The CTI program is intimately familiar with workforce management operations and has developed proficiency at pairing content with delivery mechanisms to help optimize impact. | E33: =IF(D33="N/A","N/A",3) -> 3 | F33: =IF(D33=0, "Not Implemented",IF(D33=1,"Partially Implemented",IF(D33=2,"Largely Implemented",IF(D33=3,"Fully Implemented",IF(D33="N/A","N/A"))))) -> Not Implemented
C34: e. Changes in the organization’s threat profile that are likely to impact workforce management efforts are routinely briefed to cybersecurity leadership. | E34: =IF(D34="N/A","N/A",3) -> 3 | F34: =IF(D34=0, "Not Implemented",IF(D34=1,"Partially Implemented",IF(D34=2,"Largely Implemented",IF(D34=3,"Fully Implemented",IF(D34="N/A","N/A"))))) -> Not Implemented
C35: f. Contributions to workforce management efforts are tracked, evaluated, and routinely reported to leadership. | E35: =IF(D35="N/A","N/A",3) -> 3 | F35: =IF(D35=0, "Not Implemented",IF(D35=1,"Partially Implemented",IF(D35=2,"Largely Implemented",IF(D35=3,"Fully Implemented",IF(D35="N/A","N/A"))))) -> Not Implemented
C36: Section Subtotal | D36: =SUM(D30:D35) -> 0 | E36: =SUM(E30:E35)-((COUNTIF(D30:D35,"N/A")*3)) -> 18 | F36: =D36/E36 -> 0
C38: Domain Total | D38: =D13+D27+D36 -> 0 | E38: =E13+E27+E36 -> 69 | F38: =D38/E38 -> 0

Sheet Domain 10 - ARCHITECTURE
B2: Cyber Threat Intelligence Capability Maturity Model (CTI-CMM) | F2: DATE LAST ASSESED | G2: 1/19/2026
F3: Domain is Relevant? | G3: Yes
B4: 6.9 Cybersecurity Architecture (ARCHITECTURE)
D5: SCORE | E5: MAX | F5: STATUS | G5: EVIDENCE | H5: POC | I5: NOTES
B6: 1. Support Strategy Development for the Cybersecurity Architecture
B7: CTI1 | C7: a. CTI is familiar with key personnel involved in cybersecurity architecture strategy and program development activities, providing input in at least an ad hoc manner. | E7: =IF(D7="N/A","N/A",3) -> 3 | F7: =IF(D7=0, "Not Implemented",IF(D7=1,"Partially Implemented",IF(D7=2,"Largely Implemented",IF(D7=3,"Fully Implemented",IF(D7="N/A","N/A"))))) -> Not Implemented
B8: CTI2 | C8: b. CTI has established communication channels and trusted relationships with cybersecurity architecture leadership or significant stakeholders, leveraging both regularly to proactively provide input to support cybersecurity architecture strategy and program development as intelligence insights are developed. | E8: =IF(D8="N/A","N/A",3) -> 3 | F8: =IF(D8=0, "Not Implemented",IF(D8=1,"Partially Implemented",IF(D8=2,"Largely Implemented",IF(D8=3,"Fully Implemented",IF(D8="N/A","N/A"))))) -> Not Implemented
B9: CTI3 | C9: c. CTI is fully integrated into the processes that shape the cybersecurity architecture strategy, leveraging its unique vantage point within the enterprise to provide novel insights such as risks associated with changes in the threat landscape and vendor practices or products that may impact enterprise cybersecurity architecture. (see THREAT) | E9: =IF(D9="N/A","N/A",3) -> 3 | F9: =IF(D9=0, "Not Implemented",IF(D9=1,"Partially Implemented",IF(D9=2,"Largely Implemented",IF(D9=3,"Fully Implemented",IF(D9="N/A","N/A"))))) -> Not Implemented
C10: Section Subtotal | D10: =SUM(D7:D9) -> 0 | E10: =SUM(E7:E9)-((COUNTIF(D7:D9,"N/A")*3)) -> 9 | F10: =D10/E10 -> 0
B12: 2. Support for Cybersecurity Architecture through Continuous Threat Modeling
B13: CTI1 | C13: a. CTI is engaged on an ad hoc basis by cybersecurity architecture personnel to address specific questions about technologies, exploitation of vulnerabilities, or other threat-related insights in support of architecture-planning activities. | E13: =IF(D13="N/A","N/A",3) -> 3 | F13: =IF(D13=0, "Not Implemented",IF(D13=1,"Partially Implemented",IF(D13=2,"Largely Implemented",IF(D13=3,"Fully Implemented",IF(D13="N/A","N/A"))))) -> Not Implemented
B14: CTI2 | C14: b. CTI is sufficiently familiar with the cybersecurity architecture to identify threats that cut across cybersecurity functions (potentially “slipping through the cracks” between teams) or risks manifested through the exploitation of multiple technologies and reports these regularly to the cybersecurity architecture team. | E14: =IF(D14="N/A","N/A",3) -> 3 | F14: =IF(D14=0, "Not Implemented",IF(D14=1,"Partially Implemented",IF(D14=2,"Largely Implemented",IF(D14=3,"Fully Implemented",IF(D14="N/A","N/A"))))) -> Not Implemented
C15: c. CTI reports for the cybersecurity architecture team regularly include recommendations for mitigating threats at the enterprise level. | E15: =IF(D15="N/A","N/A",3) -> 3 | F15: =IF(D15=0, "Not Implemented",IF(D15=1,"Partially Implemented",IF(D15=2,"Largely Implemented",IF(D15=3,"Fully Implemented",IF(D15="N/A","N/A"))))) -> Not Implemented
B16: CTI3 | C16: d. CTI prepares contextualized reporting and recommendations for the architecture team on a regular cadence of trends impacting controls, processes, technologies, and other elements that require enterprise-wide solutioning to resolve (e.g., discovery of extensive shadow IT, changes to product capabilities, foreign acquisition of vendors, etc.) | E16: =IF(D16="N/A","N/A",3) -> 3 | F16: =IF(D16=0, "Not Implemented",IF(D16=1,"Partially Implemented",IF(D16=2,"Largely Implemented",IF(D16=3,"Fully Implemented",IF(D16="N/A","N/A"))))) -> Not Implemented
C17: Section Subtotal | D17: =SUM(D13:D16) -> 0 | E17: =SUM(E13:E16)-((COUNTIF(D13:D16,"N/A")*3)) -> 12 | F17: =D17/E17 -> 0
B19: 3. Support for Cybersecurity Architecture through Policy & Compliance Alignment
B20: CTI1 | C20: a. CTI informs the architecture team of changes to CTI infrastructure (new tools, data storage solutions, etc.) on an ad hoc basis. | E20: =IF(D20="N/A","N/A",3) -> 3 | F20: =IF(D20=0, "Not Implemented",IF(D20=1,"Partially Implemented",IF(D20=2,"Largely Implemented",IF(D20=3,"Fully Implemented",IF(D20="N/A","N/A"))))) -> Not Implemented
C21: b. CTI reports noncompliant controls, processes, technologies, and other elements it discovers in the course of its duties to the architecture team in at least an ad hoc manner. | E21: =IF(D21="N/A","N/A",3) -> 3 | F21: =IF(D21=0, "Not Implemented",IF(D21=1,"Partially Implemented",IF(D21=2,"Largely Implemented",IF(D21=3,"Fully Implemented",IF(D21="N/A","N/A"))))) -> Not Implemented
B22: CTI2 | C22: c. CTI informs architecture stakeholders in advance of changes to CTI infrastructure and provides insights into how those changes — and any resulting capabilities — might enhance or degrade enterprise cybersecurity outcomes. | E22: =IF(D22="N/A","N/A",3) -> 3 | F22: =IF(D22=0, "Not Implemented",IF(D22=1,"Partially Implemented",IF(D22=2,"Largely Implemented",IF(D22=3,"Fully Implemented",IF(D22="N/A","N/A"))))) -> Not Implemented
C23: d. CTI aligns capabilities development and technology acquisition with cybersecurity architecture needs while ensuring compliance with policies and controls. | E23: =IF(D23="N/A","N/A",3) -> 3 | F23: =IF(D23=0, "Not Implemented",IF(D23=1,"Partially Implemented",IF(D23=2,"Largely Implemented",IF(D23=3,"Fully Implemented",IF(D23="N/A","N/A"))))) -> Not Implemented
B24: CTI3 | C24: e. CTI has documented procedures for engaging with incident response and other teams to develop novel intelligence reporting based on internal cybersecurity events that represent unrealized risk to the enterprise cybersecurity architecture and does so on a recurring basis. | E24: =IF(D24="N/A","N/A",3) -> 3 | F24: =IF(D24=0, "Not Implemented",IF(D24=1,"Partially Implemented",IF(D24=2,"Largely Implemented",IF(D24=3,"Fully Implemented",IF(D24="N/A","N/A"))))) -> Not Implemented
C25: f. CTI helps shape the cybersecurity architecture by leveraging its “trusted advisor” status to inject policy insights at the intersection of cybersecurity and business operations. | E25: =IF(D25="N/A","N/A",3) -> 3 | F25: =IF(D25=0, "Not Implemented",IF(D25=1,"Partially Implemented",IF(D25=2,"Largely Implemented",IF(D25=3,"Fully Implemented",IF(D25="N/A","N/A"))))) -> Not Implemented
C26: Section Subtotal | D26: =SUM(D20:D25) -> 0 | E26: =SUM(E20:E25)-((COUNTIF(D20:D25,"N/A")*3)) -> 18 | F26: =D26/E26 -> 0
C28: Domain Total | D28: =D10+D17+D26 -> 0 | E28: =E10+E17+E26 -> 39 | F28: =D28/E28 -> 0

Sheet Domain 11 - PROGRAM
B2: Cyber Threat Intelligence Capability Maturity Model (CTI-CMM) | F2: DATE LAST ASSESED | G2: 1/19/2026
F3: Domain is Relevant? | G3: Yes
B4: 6.10 Cybersecurity Program Management (PROGRAM)
D5: SCORE | E5: MAX | F5: STATUS | G5: EVIDENCE | H5: POC | I5: NOTES
B6: 1. Align CTI Program with Enterprise Cybersecurity Strategy
B7: CTI1 | C7: a. CTI is aware of the enterprise cybersecurity strategy and provides inputs and support to its development, in at least an ad hoc manner. | E7: =IF(D7="N/A","N/A",3) -> 3 | F7: =IF(D7=0, "Not Implemented",IF(D7=1,"Partially Implemented",IF(D7=2,"Largely Implemented",IF(D7=3,"Fully Implemented",IF(D7="N/A","N/A"))))) -> Not Implemented
B8: CTI2 | C8: b. CTI understands the enterprise cybersecurity strategy and leverages that understanding to provide focused inputs and development support on a regular basis. | E8: =IF(D8="N/A","N/A",3) -> 3 | F8: =IF(D8=0, "Not Implemented",IF(D8=1,"Partially Implemented",IF(D8=2,"Largely Implemented",IF(D8=3,"Fully Implemented",IF(D8="N/A","N/A"))))) -> Not Implemented
C9: c. The CTI program strategy and priorities are formally documented and aligned with the organization’s cybersecurity mission, strategic objectives, and risk to critical infrastructure and assets. | E9: =IF(D9="N/A","N/A",3) -> 3 | F9: =IF(D9=0, "Not Implemented",IF(D9=1,"Partially Implemented",IF(D9=2,"Largely Implemented",IF(D9=3,"Fully Implemented",IF(D9="N/A","N/A"))))) -> Not Implemented
C10: d. CTI applies its understanding of the cybersecurity program strategy to inform the development of CTI capabilities that are compliant and aligned to cybersecurity program goals. | E10: =IF(D10="N/A","N/A",3) -> 3 | F10: =IF(D10=0, "Not Implemented",IF(D10=1,"Partially Implemented",IF(D10=2,"Largely Implemented",IF(D10=3,"Fully Implemented",IF(D10="N/A","N/A"))))) -> Not Implemented
B11: CTI3 | C11: e. CTI goals and performance standards are mapped to the performance management frameworks (OKR, KPI, etc.) used by the enterprise cybersecurity program, ensuring they are working in concert. | E11: =IF(D11="N/A","N/A",3) -> 3 | F11: =IF(D11=0, "Not Implemented",IF(D11=1,"Partially Implemented",IF(D11=2,"Largely Implemented",IF(D11=3,"Fully Implemented",IF(D11="N/A","N/A"))))) -> Not Implemented
C12: f. CTI is fully integrated into the processes that shape the cybersecurity program strategy and leverages its unique vantage point within the enterprise to provide novel insights such as risks associated with business changes, changes in the global threat landscape, and changes in the enterprise threat profile. (see RISK and THREAT) | E12: =IF(D12="N/A","N/A",3) -> 3 | F12: =IF(D12=0, "Not Implemented",IF(D12=1,"Partially Implemented",IF(D12=2,"Largely Implemented",IF(D12=3,"Fully Implemented",IF(D12="N/A","N/A"))))) -> Not Implemented
C13: Section Subtotal | D13: =SUM(D7:D12) -> 0 | E13: =SUM(E7:E12)-((COUNTIF(D7:D12,"N/A")*3)) -> 18 | F13: =D13/E13 -> 0
B15: 2. Support Maturation of the Enterprise Cybersecurity Program
B16: CTI1 | C16: a. SCTI is familiar with key personnel involved in cybersecurity program management and effectively leverages this access on an ad hoc basis to provide relevant inputs. | E16: =IF(D16="N/A","N/A",3) -> 3 | F16: =IF(D16=0, "Not Implemented",IF(D16=1,"Partially Implemented",IF(D16=2,"Largely Implemented",IF(D16=3,"Fully Implemented",IF(D16="N/A","N/A"))))) -> Not Implemented
C17: b. CTI has a basic knowledge of the mission, structure, and functional components of the cybersecurity program, allowing it to craft useful insights on at least an ad hoc basis. | E17: =IF(D17="N/A","N/A",3) -> 3 | F17: =IF(D17=0, "Not Implemented",IF(D17=1,"Partially Implemented",IF(D17=2,"Largely Implemented",IF(D17=3,"Fully Implemented",IF(D17="N/A","N/A"))))) -> Not Implemented
B18: CTI2 | C18: c. CTI has established communication channels and trusted relationships with cybersecurity program leadership, leveraging both regularly to provide inputs in support of maturing the cybersecurity program. | E18: =IF(D18="N/A","N/A",3) -> 3 | F18: =IF(D18=0, "Not Implemented",IF(D18=1,"Partially Implemented",IF(D18=2,"Largely Implemented",IF(D18=3,"Fully Implemented",IF(D18="N/A","N/A"))))) -> Not Implemented
C19: d. CTI has a solid understanding of the mission, structure, and functional components of the cybersecurity program, allowing delivery of focused and properly contextualized policy inputs. | E19: =IF(D19="N/A","N/A",3) -> 3 | F19: =IF(D19=0, "Not Implemented",IF(D19=1,"Partially Implemented",IF(D19=2,"Largely Implemented",IF(D19=3,"Fully Implemented",IF(D19="N/A","N/A"))))) -> Not Implemented
B20: CTI3 | C20: e. CTI is a trusted and equal partner with other cybersecurity and IT functions in providing guidance that shapes the cybersecurity program. | E20: =IF(D20="N/A","N/A",3) -> 3 | F20: =IF(D20=0, "Not Implemented",IF(D20=1,"Partially Implemented",IF(D20=2,"Largely Implemented",IF(D20=3,"Fully Implemented",IF(D20="N/A","N/A"))))) -> Not Implemented
C21: Section Subtotal | D21: =SUM(D16:D20) -> 0 | E21: =SUM(E16:E20)-((COUNTIF(D16:D20,"N/A")*3)) -> 15 | F21: =D21/E21 -> 0
C23: Domain Total | D23: =D13+D21 -> 0 | E23: =E13+E21 -> 33 | F23: =D23/E23 -> 0
